{"settings": {"markov": {"scanner": {"__class__": "RegExpScanner", "case": 3, "expr": "(?:(?P<end>[.!?]+)|(?P<word>(?:[^\\w\\s]+|\\w+)))", "default_end": "."}, "parser": {"__class__": "Parser", "state_sizes": [1], "reset_on_sentence_end": true}, "rank": {"__class__": "Const", "size": 1, "remove": 0.0}, "formatter": {"__class__": "Formatter", "case": "TITLE", "replace": [["\\s+", " ", "U"], ["\\s*([^\\w\\s]+)\\s*", "\\1", "U"], ["([,.?!])(\\w)", "\\1 \\2", "U"], ["([\\w,.?!])([[({<])", "\\1 \\2", "U"], ["([])}>])(\\w)", "\\1 \\2", "U"], ["(\\w)([-+*]+)(\\w)", "\\1 \\2 \\3", "U"]], "end_chars": ".?!", "default_end": "."}}, "storage": {"state_separator": " "}}, "nodes": {"_ss1": {"": [[9, 11, 1, 9, 9, 8, 9, 9, 9, 4, 1, 2, 1, 9, 1, 10, 9, 1, 9, 9, 1, 8, 7, 8, 8, 5, 6, 5, 4, 1, 4, 4, 1, 1, 7, 1, 1, 1, 1, 1, 1, 1, 1, 3, 3, 3, 1, 3, 2, 1, 1, 1, 2, 1, 1, 1, 1, 1, 2, 1, 1, 1, 1, 1, 1, 1, 1, 1, 1, 1, 1, 1, 2, 1, 1, 1, 1, 1, 1, 1, 1, 2, 1, 1, 1, 1, 1, 1], ["walter", "nummus", "pios", "ii", "iii", "iv", "v", "vi", "vii", "\"", "rex", "o", "quae", "x", "abbates", "xi", "xii", "albus", "xiii", "xiv", "reliqua", "viii", "ix", "xv", "xvi", "xvii", "xviii", "xix", "xx", "quia", "xxi", "xxii", "andromachen", "inclament", "medieval", "defluit", "si", "morerentur", "felices", "auri", "tantum", "rara", "credite", "xxiii", "xxiv", "xxv", "set", "xxvi", "xxvii", "xxviii", "xxix", "xxx", "'", "dici", "potores", "pretiosa", "ex", "laudamus", "qui", "clerici", "humus", "imitemur", "magnus", "licet", "quod", "longas", "illinc", "malo", "tutius", "heu", "numquid", "juvenalis", "quid", "ego", "quo", "sponsum", "hic", "marcellusque", "carmen", "fert", "quidquid", "est", "non", "an", ",", "nam", "infulatum", "tempus"]], "walter": [18, "of"], "of": [18, "châtillon"], "châtillon": [[9, 9], ["walter", "carmen"]], "carmen": [[1, 1, 1, 1, 1, 1, 2, 1, 1], ["x", "xi", "xii", "iv", "v", "vi", "vii", "viii", "ix"]], "x": [[1, 1, 1, 1, 1, 1, 1, 1, 1, 1, 1], ["i", "frustra", "quod", "per", "in", "roma", "si", "non", "ut", "habundes", "aurum"]], "i": [[1, 1, 1, 1, 1, 1, 1, 1, 1, 1], ["captivata", "felix", "baculare", "stulti", "multiformis", "missus", "eliconis", "inter", "fallax", "dilabatur"]], "captivata": [1, "largitas"], "largitas": [[1, 1, 1, 1], ["longe", "per", ".", ","]], "longe": [[1, 1, 1], ["relegatur", "exempla", "venientem"]], "relegatur": [1, ","], ",": [[1, 7, 1, 22, 11, 11, 12, 13, 1, 2, 1, 1, 1, 1, 2, 1, 16, 23, 1, 5, 1, 1, 3, 1, 1, 17, 1, 1, 2, 1, 1, 11, 19, 1, 1, 1, 1, 1, 3, 1, 5, 1, 23, 1, 1, 1, 3, 1, 1, 1, 1, 1, 2, 5, 1, 1, 1, 1, 1, 1, 1, 1, 1, 10, 2, 1, 6, 1, 1, 1, 6, 11, 2, 1, 1, 2, 1, 1, 1, 3, 1, 1, 1, 1, 1, 2, 1, 1, 1, 1, 1, 3, 2, 1, 1, 1, 1, 1, 1, 1, 1, 1, 1, 1, 4, 1, 1, 1, 1, 2, 1, 2, 1, 1, 1, 1, 4, 10, 1, 3, 1, 1, 1, 1, 1, 1, 1, 1, 1, 1, 1, 9, 1, 1, 3, 2, 2, 4, 1, 1, 2, 1, 1, 1, 3, 5, 1, 1, 1, 1, 1, 1, 2, 1, 1, 1, 1, 2, 1, 1, 1, 1, 1, 1, 1, 1, 1, 1, 1, 1, 1, 1, 1, 1, 1, 1, 1, 1, 4, 1, 3, 1, 1, 2, 1, 1, 1, 1, 1, 1, 1, 1, 1, 2, 1, 1, 1, 1, 1, 1, 1, 1, 2, 1, 1, 1, 2, 2, 1, 1, 1, 1, 1, 1, 1, 1, 1, 1, 1, 1, 1, 1, 2, 1, 1, 1, 1, 1, 1, 1, 1, 3, 1, 1, 1, 1, 1, 1, 1, 1, 1, 1, 1, 1, 1, 1, 1, 1, 1, 1, 1, 2, 1, 1, 1, 1, 1, 1, 1, 1, 2, 1, 1, 1, 1, 1, 1, 1, 1, 1, 1, 1, 1, 1, 1, 1, 1, 2, 1, 1, 1, 1, 1, 1, 1, 3, 1, 1, 1, 1, 1, 1, 1, 1, 1, 1, 1, 1, 1, 1, 1, 1, 2, 1, 1, 1, 1, 1, 1, 1, 1, 1, 1, 1, 1, 1, 1, 1, 1, 1, 1, 1, 2, 1, 1, 1, 1, 1, 1, 1, 1, 1, 1, 1, 2, 1, 1, 1, 1, 1, 1, 1, 1, 1, 1, 1, 1, 1, 1, 1, 1, 1, 1, 1, 1, 1, 1, 2, 1, 1, 1, 1, 1, 1, 1, 1, 1, 1, 1, 1], ["exulansque", "dum", "inperat", "nummus", "iustos", "impedit", "et", "quod", "suo", "nunc", "cedet", "cuncta", "nihil", "fons", "omnes", "vendunt", "non", "si", "unus", "cujus", "communis", "penes", "nec", "pauperem", "acribus", "set", "ydropes", "judici", "nisi", "cuius", "qua", "cum", "ut", "creatorem", "prudenti", "sese", "elegerunt", "dicere", "sed", "tu", "quorum", "vicia", "qui", "\"", "inquam", "diogenes", "quid", "solem", "manus", "archa", "pontifices", "papa", "patriarcha", "quam", "symon", "atque", "discunt", "virtus", "sciptio", "baculi", "ordinamur", "scripto", "creditur", "per", "iste", "expandente", "hic", "sapienter", "parcitatis", "largitate", "quos", "quia", "ergo", "sociari", "idest", "quando", "super", "cave", "voce", "sic", "foeda", "idem", "lacessitus", "victus", "degenerat", "jam", "tersites", "paticum", "parasitum", "quidlibet", "juvenalis", "semper", "nunquamne", "mugiendo", "major", "maximus", "dominari", "virtutes", "vilipendi", "viros", "difficile", "furantur", "christum", "altaria", "quae", "cupido", "habendi", "vivens", "praesul", "quantum", "sub", "dignus", "gulae", "plectuntur", "praesules", "agatis", "de", "nam", "dabit", "unde", "quotiens", "illum", "nummi", "vobis", "quanto", "tanto", "sitit", "crescit", "ex", "ingujnis", "sicut", "in", "dat", "nescit", "que", "foras", "ipse", "homere", "audiri", "auditores", "hoc", "mercedem", "odor", "nummos", "inter", "ne", "quarum", "fascinantes", "digita", "mittuntur", "latinus", "caecum", "se", "expectes", "principes", "virum", "exagitata", "vel", "verres", "deus", "scientia", "letalis", "furtum", "lenocinia", "o", "avaritia", "gloria", "infamis", "quicquid", "gaudia", "discursus", "mundi", "tot", "facit", "totus", "dic", "spes", "sponsae", "cur", "haedus", "quo", "magis", "sincerum", "quodcumque", "acescit", "pervertit", "fovet", "india", "molles", "accipit", "nulli", "roma", "sonuit", "nemo", "quanta", "quoniam", "effrons", "ubi", "vivitur", "minus", "epulum", "potus", "cui", "-", "a", "limus", "cives", "quaerenda", "opus", "aude", "fere", "allicit", "reddit", "larga", "genere", "inde", "fulmare", "tractant", "carnis", "irruit", "suam", "rodit", "est", "adipisci", "impleri", "labitur", "quaerens", "dites", "ibis", "sciat", "sit", "hinc", "tenuisse", "perdit", "inflati", "miser", "vaca", "medio", "inflatur", "laetatur", "mox", "manifestat", "frangit", "quibusdam", "rancidulum", "desistat", "sua", "aliena", "sancti", "magna", "incipe", "mea", "versus", "munus", "nescis", "amissae", "pro", "neuter", "uterque", "quis", "illam", "saepe", "quem", "odit", "ultra", "dubito", "veniat", "michi", "stabilis", "amici", "id", "potuit", "praelati", "vilius", "coniunx", "illinc", "nil", "attamen", "aspiciens", "via", "nitimur", "ardentis", "debet", "instabile", "facilis", "hunc", "vide", "quidquid", "alternantur", "ludit", "fert", "infimis", "summis", "tendimus", "domus", "rebus", "sola", "nulla", "precor", "quocumque", "me", "omne", "hodie", "pecora", "artes", "gemmae", "mel", "sis", "melior", "corrigi", "optima", "videat", "etsi", "ferit", "cras", "necdum", "ac", "fortis", "nummorum", "conservans", "exemplorum", "nolunt", "hos", "assidos", "nunquam", "agentes", "ore", "eorum", "quotquot", "veterescunt", "vix", "exibis", "sitim", "cantabo", "pontifex", "cor", "estimo", "quare", "pastor", "vivere", "pugnato", "plebs", "spoliata", "saul", "duces", "sacrum", "spiritus", "conquassabit", "datur", "nichil", "plures", "quibus", "suas", "gedeonis", "una", "fungor", "imitantur", "immo", "loquor", "multos", "ibi", "cibis", "delet", "proximus", "vinum", "ora", "more", "fluit", "senes", "pueros"]], "exulansque": [1, "probitas"], "probitas": [[1, 1, 1, 1], ["misere", ".", "proba", "jacet"]], "misere": [[1, 1], ["fugatur", "chorus"]], "fugatur": [1, ","], "dum": [[1, 1, 1, 1, 1, 1, 1, 1, 1, 1, 1, 1, 1], ["virtuti", "aerario", "sujaceas", "probatur", "sentiret", "instinctu", "pro", "nichil", "sunt", "lascivio", "propino", "non", "licet"]], "virtuti": [[1, 1], ["veritas", "."]], "veritas": [1, "prave"], "prave": [1, "novercatur"], "novercatur": [1, ","], "inperat": [1, "cupiditas"], "cupiditas": [1, "atque"], "atque": [[1, 1, 1], ["principatur", "captivatis", "rubicundus"]], "principatur": [1, "."], ".": [207, null], "nummus": [[11, 11, 11, 1], ["vincit", "regnat", "cunctis", "deficit"]], "vincit": [11, ","], "regnat": [11, ","], "cunctis": [[11, 1, 1, 1], ["imperat", "erogatur", "debet", "sordes"]], "imperat": [[11, 1], ["reos", "omnibus"]], "reos": [[11, 2, 1], ["solvit", ",", "rei"]], "solvit": [[11, 1], [",", "nuptias"]], "iustos": [11, "ligat"], "ligat": [11, ","], "impedit": [11, "et"], "et": [[11, 2, 1, 1, 1, 4, 1, 1, 2, 1, 1, 1, 1, 1, 1, 1, 1, 1, 1, 1, 1, 1, 1, 1, 1, 1, 1, 1, 1, 1, 1, 1, 1, 1, 1, 1, 1, 1, 1, 1, 1, 1, 1, 1, 1, 1, 1, 1, 1, 1, 1, 1, 1, 1, 1, 1, 1, 1, 1, 1, 1, 1, 1, 1, 1, 1, 1, 1, 1, 1, 1, 1, 1, 1, 1, 1, 1, 1, 1, 1, 1], ["liberat", "virtutis", "solvuntur", "evadit", "expiat", ",", "ignavii", "magistri", "per", "dampnat", "modeste", "notari", "avari", "simonitas", "armilla", "torpere", "condendum", "hi", "nos", "archilevita", "tantum", "tumor", "ardescit", "capitis", "temo", "beta", "declives", "grecus", "equa", "quia", "injustitia", "naturae", "hunc", "prelatos", "vitae", "sermones", "ita", "maria", "omne", "mercantur", "abhominantur", "benignum", "ferre", "carcere", "luxus", "opum", "hic", "haec", "dido", "a", "curare", "genus", "formam", "egenus", "si", "de", "dicunt", "amoris", "scribis", "cibis", "cathedras", "doctor", "scientiae", "supplicia", "officium", "cum", "princeps", "nomina", "lugentes", "longo", "mobilis", "exultent", "validos", "quos", "revereantur", "quem", "qualis", "telis", "fidelis", "dilatat", "praelatis"]], "liberat": [[1, 1, 1, 1, 1, 1, 1, 1, 1, 1, 1], ["ii", "iii", "iv", "v", "vi", "vii", "viii", "ix", "x", "xi", "medieval"]], "ii": [[1, 1, 1, 1, 1, 1, 1, 1, 1, 1], ["solum", "olim", "ergo", "quando", "luxus", "rithmis", "accusator", "nescimus", "si", "templum"]], "solum": [[1, 1, 1], ["nec", "forti", "legere"]], "nec": [[3, 1, 1, 1, 1, 1, 1, 1, 1, 1, 1, 1, 1, 1, 1], ["in", "dant", "quantum", "recenter", "sine", "surgit", "defunctus", "avarus", "jam", "afflatus", "simonia", "regnabant", "parcit", "christi", "aures"]], "in": [[1, 1, 1, 1, 1, 1, 1, 1, 1, 1, 1, 1, 1, 1, 3, 1, 1, 1, 2, 1, 1, 1, 1, 1, 1, 2, 1, 2, 1, 1, 1, 1, 1, 1, 2, 1, 1, 1, 1, 1, 1, 1, 1, 1, 1, 1, 1, 1, 1, 1, 1, 1, 1, 1, 1, 1, 1, 1, 1, 1, 1, 1, 1, 1, 1, 1, 1], ["precio", "insidiis", "mediis", "sola", "execrabili", "hoc", "quantum", "avaris", "deserto", "baculo", "propatulo", "aperto", "latebris", "tenebris", "quo", "illos", "subditos", "cacabo", "habitum", "arca", "terris", "his", "nummo", "pretio", "franciam", "una", "vulgus", "primis", "poculis", "tumorem", "claustris", "via", "facinus", "secreto", "vetitum", "vineam", "imum", "limum", "sinodis", "electionibus", "tempore", "vinculis", "hortis", "bonitate", "diversa", "personis", "humanis", "virtute", "portis", "lutum", "christo", "pace", "bellorum", "pecuniae", "circuitu", "corde", "peccatum", "capite", "moenibus", "coelis", "conspectu", "domo", "se", "terra", "tribunal", "melotis", "qua"]], "precio": [[1, 1], ["precium", "domant"]], "precium": [1, "habetur"], "habetur": [1, ","], "virtutis": [[1, 1, 1, 1], ["mentio", "penitus", ".", "insectantur"]], "mentio": [[1, 1], ["penitus", ","]], "penitus": [[1, 1, 1, 1, 1, 1, 1], ["deletur", "nunc", "sunt", "ordinem", "redditur", "ficus", "criminum"]], "deletur": [1, ","], "quod": [[1, 1, 1, 1, 1, 3, 1, 1, 1, 1, 1, 1, 1, 1, 1, 1, 1, 1, 1, 1, 1, 1, 1, 1, 1, 1], ["veretur", "fugisti", "est", "sola", "philosophi", "non", "fecisti", "loqui", "rubrum", "a", "coivit", "fidelis", ",", "cuncti", "vix", "decuit", "opes", "semper", "superbia", "dicunt", "si", "natura", "multiplicat", "eos", "futuri", "hos"]], "veretur": [[1, 1], ["ratio", ","]], "ratio": [[1, 1], ["nemo", "male"]], "nemo": [[1, 1, 1, 1, 1, 1], ["jam", "suscitatur", ".", "tuum", "feliciter", "poterit"]], "jam": [[1, 1, 1, 1, 1, 1, 1, 1, 1, 1, 1, 1, 1, 1], ["veretur", "nebulonizat", "prorsus", "caritas", "loquitur", "plus", "casura", "remoto", "virtutum", "loquar", "furantur", "mendicat", "columpnae", "praelatos"]], "suo": [1, "dum"], "aerario": [1, "quicquam"], "quicquam": [1, "applicetur"], "applicetur": [1, "."], "iii": [[1, 1, 1, 1, 1, 1, 1, 1, 1, 1], ["quondam", "hinc", "lignum", "festis", "tot", "licet", "dicta", "cur", "set", "patrum"]], "quondam": [[1, 1], ["diffusissimum", ","]], "diffusissimum": [1, "verbum"], "verbum": [[1, 1, 1, 1], ["do", "nobilissimum", "desine", "de"]], "do": [1, "-"], "-": [[1, 1, 1], ["das", "dedi", "ne"]], "das": [1, "-"], "dedi": [1, ","], "nunc": [[3, 1, 1, 1, 1, 1, 1, 1, 1, 1, 1, 1, 1], ["est", "sunt", "debet", "leguntur", "acquirunt", "imitator", "haberet", "de", "ago", "pharisea", "vivit", "habet", "temporis"]], "est": [[1, 1, 1, 2, 1, 1, 5, 1, 1, 1, 1, 1, 1, 1, 9, 2, 1, 1, 1, 1, 2, 1, 1, 1, 1, 1, 1, 1, 1, 2, 1, 2, 1, 1, 1, 1], ["angustissimum", "pessimum", "judicii", "quod", "dominium", "nostrum", "in", "inventum", "via", "michi", "animus", "satiram", "summus", "abbas", ",", "et", "melle", "quam", "prae", "illius", "quodam", "scire", "jacuisse", "quasi", "hujsmodi", "forsitan", "reverendus", "sancta", "luto", "hodie", "etenim", "virtus", "phebo", "haec", "ut", "qui"]], "angustissimum": [1, "plusquam"], "plusquam": [1, "possit"], "possit": [1, "credi"], "credi": [1, ";"], ";": [[1, 1, 1, 1, 2, 1, 1, 7, 1, 1, 1, 1, 1, 1, 1, 1, 1, 1, 5, 1, 1, 1, 1, 1, 1, 1, 1, 1, 1, 1, 1, 1, 1, 1, 1, 1, 1, 1, 1, 2, 1, 1, 1, 1, 2, 1, 1, 1, 1, 1, 1, 1, 1, 1, 1, 1, 1, 1, 1, 1, 1, 1, 1, 1, 1, 1, 1, 1, 1, 1, 1, 1, 1, 1, 1, 1, 1, 1, 1, 1], ["verbum", "praesulum", "tamen", "ferens", "sic", "nullum", "ab", "nam", "illa", "ibi", "istud", "notate", "transit", "elisei", "tali", "quia", "quare", "illos", "set", "derogare", "versa", "temprore", "nolunt", "fallit", "impletur", "hoc", "nolle", "si", "esto", "de", "alterius", "nulla", "vox", "omne", "solus", "fulmarum", "hii", "cum", "in", "ergo", "imitemur", "o", "intronizat", "quis", "quod", "licet", "vitiosus", "utrobique", "nescio", "sponsa", "veniat", "que", "unam", "aurum", "ubinam", "veni", "viatores", "quid", "a", "mors", "universos", "nonne", "male", "confundantur", "hi", "eo", "inde", "jacob", "idem", "sacros", "vendunt", "simonia", "non", "huic", "credo", "alienas", "jam", "forum", "hiemali", "viros"]], "nobilissimum": [1, "quod"], "fugisti": [1, "redi"], "redi": [1, ","], "cedet": [1, "quod"], "pessimum": [1, "gratia"], "gratia": [[1, 1], ["mercedi", "procul"]], "mercedi": [1, "."], "iv": [[1, 1, 1, 1, 2, 1, 1, 1, 1, 1], ["exulante", "hinc", "illa", "i", "cum", "cur", "ecce", "hic", "ubi", "excaecati"]], "exulante": [1, "gratia"], "procul": [[1, 1, 1, 1], ["largitatis", "non", "quies", "ab"]], "largitatis": [[1, 1], [",", ";"]], "cuncta": [1, "sunt"], "sunt": [[1, 1, 1, 1, 1, 1, 1, 1, 1, 1, 4, 1, 1, 1, 1, 1, 1, 1, 1, 1], ["venalia", "ablatjvi", "adversativi", "deformes", "carnes", "virtutum", "medii", "discrimina", "imbuti", "juniores", ",", "fornicarii", "hi", "nuper", "vestimenta", "ecclesiam", "cenam", "quos", "semen", "rei"]], "venalia": [1, ","], "nihil": [1, "datur"], "datur": [[1, 2, 1], ["gratis", "ultra", "nil"]], "gratis": [[1, 1], [";", "tribuunt"]], "praesulum": [[1, 1], ["marsupia", "sophisma"]], "marsupia": [1, "vi"], "vi": [[1, 1, 1, 1, 1, 1, 1, 1, 1, 1, 1, 1, 1, 1], ["tenacitatis", "sed", "gaudes", ".", "per", "ecce", "heu", "i", "haec", "modernorum", "a", "omnis", "in", "praebende"]], "tenacitatis": [1, "stringit"], "stringit": [1, "avaritia"], "avaritia": [[2, 1, 1], [",", "mentibus", "rebus"]], "fons": [[1, 1], ["iniquitatis", "diviciarum"]], "iniquitatis": [1, "."], "v": [[1, 1, 1, 1, 1, 1, 1, 1, 1, 1, 1], ["fuerant", "unde", "ut", "spargat", "i", "in", "qui", "fortassis", "vide", "nil", "terminabit"]], "fuerant": [1, "antiquitus"], "antiquitus": [[1, 1, 1], ["praesules", "artium", "dici"]], "praesules": [[1, 3, 1, 1, 1, 1], ["dativi", ",", "moderni", "hoc", "rectam", "christum"]], "dativi": [1, ","], "omnes": [[1, 1, 2, 1, 1, 1, 1, 1, 1, 1], ["pene", "avaritia", ",", "discunt", "dissoluti", "ad", "rei", "fines", "in", "avariciae"]], "pene": [[1, 1], ["penitus", "curae"]], "ablatjvi": [1, ","], "adversativi": [1, ","], "vendunt": [[2, 1, 1, 1, 1, 1], [",", "sponsae", "hodie", "et", "ordines", "crisma"]], "non": [[1, 2, 1, 4, 1, 1, 1, 1, 1, 1, 2, 1, 1, 1, 1, 2, 1, 1, 1, 1, 1, 2, 1, 2, 1, 2, 1, 1, 1, 1, 1, 1, 1, 1, 1, 1, 1, 1, 1, 1, 1, 1, 1, 1, 1, 1, 1, 1, 1, 1], ["dant", "in", "naturae", "est", "potes", "hiis", "audent", "quaerunt", "sine", "quaerit", "minus", "scribere", "solent", "metuunt", "intrat", "bene", "ambiguum", "hospes", "avarus", "respondent", "sint", "datur", "amatis", "habet", "se", "hunc", "fodit", "custodit", "erat", "qui", "debebam", "sim", "curata", "trahit", "ignorat", "minor", "prosunt", "sis", "exemplum", "differas", "placet", "habentes", "cogitant", "recipere", "vidit", "taceo", "aequum", "compescitur", ",", "regunt"]], "dant": [[1, 1], ["redditus", "locum"]], "redditus": [[1, 1], ["hospiti", "auri"]], "hospiti": [1, "vel"], "vel": [[1, 1, 1, 1, 1, 1, 1, 1, 1, 1, 1, 1, 2, 1, 1, 1, 1, 1], ["civi", "argenti", "pontifex", "ementulari", "perimi", "precio", "numquam", "proditor", "spretores", "per", "avari", "abuti", "haec", "occulta", "athenis", "nequibis", "quem", "rectus"]], "civi": [1, "."], "sed": [[1, 1, 1, 1], ["cur", "maiorem", "ne", "in"]], "cur": [[1, 1, 1, 1, 1, 1, 1, 1], ["generaliter", "mores", "sequi", "michi", "struis", "libros", "odiens", "per"]], "generaliter": [1, "dixi"], "dixi": [[1, 1], [",", "domine"]], "si": [[1, 1, 1, 1, 2, 1, 2, 1, 1, 1, 1, 1, 1, 1, 1, 1, 1, 1, 1, 2, 1, 2, 2, 2, 2, 1, 1, 1, 1, 1, 1, 1, 1, 1, 1, 1, 1, 1, 1, 1, 1, 1, 1, 1, 1], ["quaeratur", "quisquam", "nunc", "per", "forte", "detur", "quis", "quid", "facinus", "spectes", "rem", "nummus", "nummo", "cupiam", "recte", "de", "natura", "scires", "tendimus", "vis", "genus", "me", "non", "nichil", "pauper", "vixerit", "joseph", "tot", "filiis", "paupertas", "populus", "montis", "archam", "socrates", "dives", "velimus", "pono", "virtutem", "potest", "perdimus", "stultus", "es", "pollutus", "velis", "liceat"]], "quaeratur": [1, ","], "unus": [1, "specialiter"], "specialiter": [1, "ut"], "ut": [[1, 1, 1, 1, 1, 1, 1, 1, 1, 1, 1, 1, 1, 1, 1, 1, 1, 1, 1, 1, 1, 1, 1, 1, 1, 1, 1, 1, 1, 1, 1, 1], ["excipiatur", "rapiant", "fatua", "apostolica", "solummodo", "occultum", "testatur", "jungatur", "a", "judaeis", "tanto", "plebs", "thebarum", "sic", "iam", "ocultis", "aeternam", "inceperit", "virtus", "piscibus", "stes", "laetentur", "in", "ipsimet", "cervus", "thesauros", "jam", "laudare", "verum", "sunt", "det", "subjectis"]], "excipiatur": [1, ","], "cujus": [[1, 1, 1, 1, 1], ["dissimiliter", "autem", "erat", "in", "nemo"]], "dissimiliter": [1, "bursa"], "bursa": [[1, 1], ["dispensatur", ","]], "dispensatur": [1, ","], "communis": [1, "communiter"], "communiter": [1, "cunctis"], "erogatur": [1, "."], "vii": [[1, 1, 1, 1, 1, 1, 1, 1, 2, 1, 1], ["omni", "me", "ligno", "jam", "dic", "adora", "i", "suam", "a", "mors", "inaudita"]], "omni": [1, "pene"], "curae": [1, "praesident"], "praesident": [1, "incurii"], "incurii": [1, ","], "penes": [1, "quos"], "quos": [[1, 1, 1, 1, 1, 1, 1, 1, 1, 1, 1, 1, 1, 2, 1], ["justitiae", "accusat", "et", "nemo", "inquinat", "operit", "cum", "prece", "ad", "hereses", "timidos", "nunquam", "dona", "venit", "domus"]], "justitiae": [1, "tenor"], "tenor": [1, "est"], "judicii": [1, "."], "pios": [1, "ligant"], "ligant": [1, "impie"], "impie": [1, ","], "solvuntur": [1, "impii"], "impii": [1, ","], "locum": [[1, 1, 1, 1], ["veniae", "nunc", "dare", "sibi"]], "veniae": [1, "sine"], "sine": [[1, 1, 1, 1, 1, 1, 1, 1, 1], ["sorte", "dispendio", "solis", "mysterio", "misterio", "crimine", "macula", "divitiis", "poculo"]], "sorte": [1, "praemii"], "praemii": [1, "."], "viii": [[1, 1, 1, 1, 1, 1, 1, 1, 1, 1, 1], ["sedent", "quem", "ibi", "studet", "roma", "disputet", "sponsa", "cum", "i", "isti", "jam"]], "sedent": [1, "in"], "insidiis": [1, ","], "pauperem": [1, "ut"], "rapiant": [1, ","], "acribus": [1, "angariis"], "angariis": [1, "seminudus"], "seminudus": [1, "spoliant"], "spoliant": [1, ","], "set": [[1, 1, 1, 1, 1, 1, 1, 1, 1, 1, 2, 1, 1, 1, 1, 1, 1, 1, 1, 1, 1, 1, 1, 1, 1, 1, 1, 1, 1, 1, 1], ["referti", "defunctus", "id", "cum", "est", "nummi", "neque", "a", "nostris", "naso", "ne", "audiat", "auctorem", "quoniam", "vi", "cui", "secundum", "nunc", "sponsum", "nitimur", "nec", "hic", "non", "amare", ",", "et", "moderni", "ausculta", "disperdet", "nil", "me"]], "referti": [1, "spoliis"], "spoliis": [1, "praede"], "praede": [1, "magis"], "magis": [[1, 1, 1, 1, 1, 1], ["inhiant", "locuples", "intumescit", "approbo", "fiunt", "patitur"]], "inhiant": [1, ","], "ydropes": [1, "in"], "mediis": [1, "sitim"], "sitim": [[1, 1], ["rebus", "quod"]], "rebus": [[1, 1, 1, 1, 1], ["ampliant", "dissolutis", "erubescit", ".", "vitam"]], "ampliant": [1, "."], "ix": [[1, 1, 1, 1, 1, 1, 1, 1, 1, 1], ["hodie", "quid", "jacob", "roma", "sciat", "hinc", "igitur", "omnes", "i", "jam"]], "hodie": [[1, 2, 1, 1, 1, 1], ["jus", ",", "novi", "virtus", "si", "vix"]], "jus": [[1, 1, 1], ["emitur", "sine", "conditionis"]], "emitur": [1, "magno"], "magno": [1, "quidem"], "quidem": [1, "pretio"], "pretio": [[2, 1], [",", "pretium"]], "judici": [1, "tribuitur"], "tribuitur": [1, "totique"], "totique": [1, "collegio"], "collegio": [1, ";"], "tamen": [[1, 1, 1, 1], ["haut", "spes", "facilis", "exitus"]], "haut": [1, "perficitur"], "perficitur": [1, "jus"], "dispendio": [1, "nisi"], "nisi": [[1, 1, 1, 1], ["rursus", "doni", "vas", "fallit"]], "rursus": [1, "sequitur"], "sequitur": [[1, 1, 1], ["muneris", "hunc", "doctores"]], "muneris": [1, "oblatio"], "oblatio": [1, "."], "frustra": [1, "gemens"], "gemens": [1, "vidua"], "vidua": [1, "preces"], "preces": [1, "fundit"], "fundit": [1, "hodie"], "doni": [1, "congrua"], "congrua": [1, "condiantur"], "condiantur": [1, "specie"], "specie": [[1, 1], [";", "virtutis"]], "ferens": [1, "nil"], "nil": [[1, 1, 1, 1, 1, 1, 1], ["ut", "scribens", "michi", "volunt", "aut", "gratis", "credunt"]], "fatua": [1, "limen"], "limen": [[1, 1], ["intrat", "."]], "intrat": [[1, 1, 1], ["curiae", "faemina", ","]], "curiae": [1, "manis"], "manis": [1, "enim"], "enim": [[1, 1, 1, 1, 1, 1, 1], ["vacua", "imperat", "leccatores", "respondentem", "vitium", "criminis", "ciconias"]], "vacua": [1, "nichil"], "nichil": [[1, 1, 1, 2, 1, 1], ["habet", "obiciam", "est", "attuleris", "posse", "absque"]], "habet": [[1, 1, 1, 1, 1, 1, 1, 1], ["gratiae", "fidei", "barbaris", "comitem", "unde", "patronum", "paulinus", "consimiles"]], "gratiae": [1, "."], "xi": [[1, 1, 1, 1, 1, 1, 1, 1, 1, 1, 1, 1], ["redimuntur", "i", "si", "libro", "vis", "ut", "eligendi", "quid", "illi", "virtus", "ex", "evangelizantium"]], "redimuntur": [1, "scelera"], "scelera": [1, "mediante"], "mediante": [[1, 1], ["pretio", "baculo"]], "cuius": [1, "offert"], "offert": [1, "dextera"], "dextera": [1, "mundus"], "mundus": [[1, 1, 1, 1, 1, 1, 1], ["abit", ",", "et", "nummo", "compati", "universus", "viribus"]], "abit": [1, "vitio"], "vitio": [[1, 1, 1, 1, 1], ["et", "vitium", "sepultas", "virtus", "veneris"]], "evadit": [1, "aspera"], "aspera": [1, ","], "expiat": [1, "ultio"], "ultio": [1, ";"], "sic": [[1, 1, 1, 1, 1, 1, 1, 1, 1, 1, 1, 1, 1, 1], ["excusant", "et", "in", "praetextatos", "sacerdos", "ordiar", "fuisse", "impletum", "eligitur", "ait", "moderni", "instituit", "pascunt", "desiderat"]], "excusant": [1, "munera"], "munera": [[1, 1, 1], ["quos", ",", "praelatorum"]], "accusat": [1, "actio"], "actio": [1, "."], "medieval": [9, "latin"], "latin": [[9, 9], ["the", "library"]], "the": [[9, 9], ["latin", "classics"]], "library": [9, "the"], "classics": [9, "homepage"], "homepage": [9, "."], "felix": [1, "erat"], "erat": [[1, 1, 1, 1, 1, 1], ["studium", "veritate", "cura", "tegimen", "a", "eligendus"]], "studium": [[1, 1], ["illa", "repellam"]], "illa": [[1, 1, 1], ["sub", "siccat", "mergit"]], "sub": [[1, 1, 1, 1, 1, 1, 1, 1], ["aetate", "jugo", "pedibus", "lege", "quo", "fago", "phebo", "tributo"]], "aetate": [1, ","], "qua": [[1, 1, 1], ["fuerunt", "nunc", "verum"]], "fuerunt": [1, "primitus"], "primitus": [[1, 1], ["artes", "sua"]], "artes": [[1, 1, 1], ["mundo", "aliquis", "."]], "mundo": [[1, 1, 1], ["datae", "dissertere", "te"]], "datae": [1, ","], "cum": [[1, 1, 1, 1, 1, 1, 1, 1, 1, 1, 1, 1, 1, 2, 1, 1, 1, 1, 1, 1, 1, 1, 1, 1, 1, 1, 1, 1], ["in", "rex", "maerore", "sua", "sint", "nebulone", "prudentibus", "bene", "videam", "talia", "suis", "semel", "mundum", "sis", "quanto", "se", "latenter", "ratio", "non", "glalicis", "sit", "parvis", "ubique", "passim", "rotundent", "plus", "modo", "secare"]], "sola": [[1, 1, 1], ["pretium", "pauperies", "virtus"]], "pretium": [[1, 1], ["erat", "nunc"]], "veritate": [1, ","], "execrabili": [1, "questus"], "questus": [1, "vanitate"], "vanitate": [1, "."], "olim": [[1, 1], ["apud", "excaecatus"]], "apud": [[1, 1], ["veteres", "se"]], "veteres": [[1, 1], ["summa", ","]], "summa": [1, "erat"], "cura": [[1, 1], ["de", "ne"]], "de": [[1, 1, 1, 1, 1, 1, 1, 1, 1, 1, 2, 1, 1, 1, 1, 1, 1, 1, 1, 1, 1, 1, 1, 1, 1], ["mundo", "quo", "amaro", "avaro", "futurae", "vitio", "gestis", "nocte", "te", "moribus", "virtute", "taydibus", "sabinis", "futura", "scientia", "pede", "qua", "socrate", "corde", "nare", "salute", "flore", "deo", "via", "coelis"]], "dissertere": [1, "rerumque"], "rerumque": [1, "natura"], "natura": [[1, 2], ["et", "negat"]], "apostolica": [1, "perhibet"], "perhibet": [1, "scriptura"], "scriptura": [1, ","], "creatorem": [[1, 1], ["cognita", ","]], "cognita": [1, "nosse"], "nosse": [1, "creatura"], "creatura": [1, "."], "hinc": [[1, 1, 1, 1, 1, 1, 1, 1], ["nimirum", "est", "scolares", "usura", "me", "francorum", "turba", "sit"]], "nimirum": [1, "studia"], "studia": [1, "sequi"], "sequi": [[1, 1], ["mente", "vestigia"]], "mente": [[1, 1, 1, 1], ["pura", "pertractatis", "prodeant", "colendus"]], "pura": [[1, 1], [",", "mente"]], "naturae": [[1, 1], ["temere", "penitus"]], "temere": [1, "depravare"], "depravare": [1, "jura"], "jura": [[1, 1], [",", "leccatorum"]], "prudenti": [[1, 1], ["colligere", ","]], "colligere": [1, "tandem"], "tandem": [1, "conjectura"], "conjectura": [1, ","], "pauperies": [1, "vita"], "vita": [[1, 1, 1, 1, 1], ["sit", ".", "est", "proavorum", "pro"]], "sit": [[1, 1, 1, 1, 1, 1, 1, 1, 1], ["secura", "aut", "vel", "vanitas", "auctorum", "obliquus", "pura", "tamen", "procul"]], "secura": [[1, 1], [".", "libido"]], "philosophi": [1, "quidam"], "quidam": [[1, 1, 1], ["incitati", "celebri", "de"]], "incitati": [1, ","], "sese": [1, "voluntariae"], "voluntariae": [1, "dantes"], "dantes": [1, "paupertati"], "paupertati": [1, ","], "elegerunt": [1, "potius"], "potius": [[1, 1, 1], ["mala", "praetores", "potibus"]], "mala": [1, "mundi"], "mundi": [[1, 1, 1, 1, 1, 1], ["pati", "respuimus", "climate", "tot", "corruit", "speciebus"]], "pati": [1, "quam"], "quam": [[1, 1, 1, 1, 1, 1, 1, 1, 1, 1, 1, 1], ["frui", "utilis", "baculus", "faemina", "nugatorii", "duri", "dispares", "habere", "triste", "diu", "quaerer", "non"]], "frui": [1, "deliciis"], "deliciis": [1, "sub"], "jugo": [1, "peccati"], "peccati": [1, "."], "unde": [[1, 1, 1, 1, 1], ["quidam", "quosdam", "conqueror", "gemo", "suum"]], "celebri": [1, "dignus"], "dignus": [[1, 1, 1, 1], ["laude", "laudis", "christi", "vitae"]], "laude": [1, "coli"], "coli": [1, "alexandro"], "alexandro": [1, "principi"], "principi": [1, "\""], "\"": [[1, 2, 1, 1, 1, 1, 1, 1, 1, 1, 1, 1, 1], ["licet", "inquit", "soli", "non", "inhiare", "ix", "disputavi", "et", "si", "ego", "xix", "nonne", "xx"]], "licet": [[1, 2, 1, 1, 1, 1], ["\"", "venias", "autem", "aenigmatica", "enim", ","]], "inquit": [2, "\""], "soli": [1, "sis"], "sis": [[1, 1, 1, 1, 1, 1], ["totius", "pejor", "eger", "immemor", "me", "in"]], "totius": [1, "dominus"], "dominus": [[2, 1, 1, 1, 1], [",", "virtutum", "praemia", "praesulum", "iter"]], "dicere": [1, "te"], "te": [[1, 1, 1, 1], ["noli", "dilatet", ",", "gratum"]], "noli": [1, "regem"], "regem": [1, ","], "sujaceas": [1, "peccatorum"], "peccatorum": [1, "moli"], "moli": [1, "."], "gaudes": [1, "victis"], "victis": [1, "hostibus"], "hostibus": [1, "atque"], "captivatis": [1, ","], "maiorem": [1, "pateris"], "pateris": [1, "vim"], "vim": [1, "captivitatis"], "captivitatis": [1, "ire"], "ire": [1, ","], "tu": [[1, 1, 1], ["virtutibus", "petisti", "si"]], "virtutibus": [1, "exulas"], "exulas": [1, "ablatis"], "ablatis": [1, ";"], "nullum": [1, "est"], "dominium": [1, "gravius"], "gravius": [1, "peccatis"], "peccatis": [[1, 1], [".", "ulcio"]], "me": [[1, 1, 1, 1, 1, 1, 1, 1, 1, 1, 1, 1, 1, 1, 1, 1, 1], ["michique", "penetrare", "verbis", "vobis", "repatriare", "bipedem", "canino", "rapit", "rheus", "felicem", "cum", "desertam", "constanter", "sequetur", "fuge", "forsan", "cogit"]], "michique": [1, "similes"], "similes": [[1, 1], ["reges", "nunc"]], "reges": [[1, 2], ["esse", ","]], "esse": [[1, 1, 1, 1, 1, 1, 1, 1, 1], ["puta", "fero", "ditiorem", "mutus", "pium", "mundo", "locuples", "stulta", "novimus"]], "puta": [1, ","], "quorum": [[1, 1, 1, 1, 1, 1], ["conscientia", "jacent", "mores", "si", "sine", "intima"]], "conscientia": [1, "manet"], "manet": [[1, 1], ["impolluta", "rata"]], "impolluta": [1, ","], "vicia": [1, "sub"], "pedibus": [1, "quorum"], "jacent": [[1, 1], ["muta", ","]], "muta": [1, ","], "qui": [[1, 1, 1, 1, 1, 1, 1, 4, 1, 1, 1, 1, 1, 1, 1, 1, 1, 1, 1, 1, 1, 1, 1, 1, 1, 1, 1, 1, 1, 1], ["mundi", "per", "nunc", "vivunt", "semper", "largi", "sors", "sunt", "ecclesiam", "mechantur", "naturam", "virtutes", "deos", "philosophantur", "de", "talibus", "sic", "defendit", "non", "velint", "corpus", "in", "vix", "bursae", "male", "vita", "pro", "parum", "nil", "subjectos"]], "respuimus": [1, "opes"], "opes": [[1, 1, 1], ["quasi", "his", "irritamenta"]], "quasi": [[1, 1, 1], ["sputa", "mortis", "reprobatus"]], "sputa": [1, "\"."], "\".": [[1, 1], ["viii", "xvii"]], "quem": [[1, 1, 1, 1, 1, 1], ["cum", "neges", "coniunx", "meus", "condam", "vincimus"]], "rex": [[1, 1], ["muneribus", "parabat"]], "muneribus": [1, "vellet"], "vellet": [1, "onerare"], "onerare": [1, ","], "nostrum": [1, "opibus"], "opibus": [[1, 1, 1, 1], ["\"", "affluere", "dives", "in"]], "inhiare": [1, ","], "ne": [[1, 1, 1, 3, 1, 2, 1, 1, 1, 1], ["michi", "res", "defendet", "quis", "longe", "vos", "permittas", "pondere", "tardaveris", "consimili"]], "michi": [[1, 1, 1, 1, 1, 1], ["subtrahas", "resonans", "turpe", "sufficit", "facti", "rescribas"]], "subtrahas": [1, ","], "potes": [1, "dare"], "dare": [[1, 1, 1], ["sine", "leccatoribus", "vago"]], "solis": [1, "radios"], "radios": [1, "ad"], "ad": [[1, 1, 1, 2, 1, 1, 1, 1, 1, 1, 1, 1, 1, 1, 1, 1, 1], ["me", "baculum", "figuram", "coronam", "pecus", "vitia", "imum", "officium", "mortem", "rem", "mentes", "nuptias", "finem", "humilium", "ea", "fontes", "forum"]], "penetrare": [1, "!"], "!": [18, null], "quid": [[1, 1, 2, 1, 1, 1, 1, 1, 1, 1, 1, 1, 1, 1, 1, 1], [",", "est", "enim", "irem", "mirum", "prodest", "valet", "ad", "confert", "tityrus", "philosophari", "dubitas", "me", "dixisse", "inducias", "sequatur"]], "inquam": [1, ","], "diogenes": [[1, 1], [",", "fuit"]], "fecisti": [1, "?"], "?": [41, null], "parabat": [1, "munera"], "solem": [1, "tu"], "petisti": [1, "?"], "o": [[1, 1, 3, 1, 1], ["si", "nummi", "cives", "circeae", "quicumque"]], "quisquam": [1, "diceret"], "diceret": [1, "hoc"], "hoc": [[1, 1, 1, 2, 1, 1, 1, 1, 1, 1], ["sub", "parca", "lignum", "est", "omnes", "idcirco", "usque", "crimen", "solum", "pharisaei"]], "lege": [[1, 1], ["christi", "matrimonii"]], "christi": [[1, 1, 1, 1], ["!", "nuptiis", "coniugis", "familiis"]], "quae": [[1, 2, 1, 1], ["pauli", "non", "tanta", "in"]], "pauli": [1, "sententia"], "sententia": [1, "conferretur"], "conferretur": [1, "isti"], "isti": [[1, 1], ["!", "sunt"]], "hiis": [[1, 1], ["temporibus", "opponet"]], "temporibus": [1, "mens"], "mens": [1, "est"], "parca": [2, ","], "autem": [[1, 1, 1, 1], ["refugit", "nubere", "velle", "proferam"]], "refugit": [1, "bursa"], "manus": [1, ","], "archa": [[1, 1], ["?", ","]], "abbates": [1, ","], "pontifices": [[1, 1], [",", "et"]], "papa": [[2, 1, 1], [",", "secundus", "statuendus"]], "patriarcha": [[1, 1, 1], ["quod", ",", "?"]], "audent": [1, "facinus"], "facinus": [[1, 1, 1], ["imperante", "aequat", "omnes"]], "imperante": [1, "marca"], "marca": [[1, 1], ["!", "."]], "debet": [[1, 1, 1, 1], ["aliqua", "et", ",", "prorsus"]], "aliqua": [1, "provehi"], "provehi": [1, "persona"], "persona": [1, ","], "quaerunt": [[1, 1], [",", "implementum"]], "utilis": [1, "sit"], "aut": [[1, 1, 1], ["quantum", "nunquam", "parum"]], "quantum": [[1, 1, 1, 1, 1, 1], ["bona", "scientiae", "alios", "quisque", "ipsa", "est"]], "bona": [1, "nec"], "scientiae": [[1, 1], ["floreat", "cultu"]], "floreat": [1, "corona"], "corona": [1, ","], "alios": [[1, 1], ["vincant", "gladios"]], "vincant": [1, "ejus"], "ejus": [1, "dona"], "dona": [[1, 1], [".", "spiritus"]], "xii": [[1, 1, 1, 1, 1, 1, 1, 1, 1, 1], ["iam", "i", "hic", "omnes", "proh", "illud", "mea", "quid", "sic", "aret"]], "iam": [[1, 1], ["roma", "dicat"]], "roma": [[1, 1, 1, 1, 1], ["fit", "datis", "solvit", "metit", ","]], "fit": [[1, 1, 1, 1, 1, 1, 1], ["altera", "papa", "largus", "equus", "mentio", "questio", "spelunca"]], "altera": [1, "totus"], "totus": [[1, 1, 1], ["fere", "est", "lucri"]], "fere": [[1, 1], ["mundus", "mentes"]], "symon": [1, "enim"], "omnibus": [[1, 1, 3, 1, 1, 1], ["inmundus", "est", ",", "locum", "mira", "haec"]], "inmundus": [1, "."], "albus": [1, "deus"], "deus": [[1, 1, 1], ["colitur", "reputaberis", "omne"]], "colitur": [1, ","], "rubicundus": [1, "non"], "mysterio": [1, "fit"], "secundus": [1, "."], "xiii": [[1, 1, 1, 1, 1, 1, 1, 1, 1], ["hinc", "per", "a", "coenobita", "quidam", "jam", "hiis", "qui", "cum"]], "scolares": [1, "desides"], "desides": [1, "fiunt"], "fiunt": [[1, 1, 1], ["et", "avidi", "vile"]], "ignavii": [1, ","], "discunt": [[1, 1], [",", "ante"]], "solummodo": [[1, 1], ["dicant", "quaerunt"]], "dicant": [1, "\""], "disputavi": [1, "!"], "loqui": [[1, 1], ["debeo", ","]], "debeo": [1, "cum"], "maerore": [1, "gravi"], "gravi": [1, ","], "virtus": [[1, 1, 1, 1, 1, 1, 1, 1], ["jacet", "crimina", "scipionum", "placidis", "hominis", "inhabitet", "prodest", "quam"]], "jacet": [[1, 1], ["artium", "improbata"]], "artium": [[1, 1], ["spreta", "doctores"]], "spreta": [1, "cum"], "sua": [[1, 1, 1, 1, 1], ["vi", "clio", "nummorum", "thura", "semper"]], "xiv": [[1, 1, 1, 1, 1, 1, 1, 1, 1], ["superficientes", "tegit", "vos", "jam", "idcirco", "set", "o", "quis", "non"]], "superficientes": [1, "libri"], "libri": [1, "nunc"], "leguntur": [1, ","], "magistri": [1, "nomine"], "nomine": [[1, 1], ["plures", "pro"]], "plures": [[1, 1, 1], ["abutuntur", "sodomaeos", "reaedificant"]], "abutuntur": [1, "."], "reliqua": [1, "desunt"], "desunt": [1, "medieval"], "baculare": [1, "sacramentum"], "sacramentum": [1, "nec"], "recenter": [1, "est"], "inventum": [1, "nec"], "misterio": [1, ";"], "ab": [[1, 1, 1, 1, 2, 1, 1, 1, 1], ["antiquo", "illis", "homine", "hercule", "omnibus", "hospite", "istis", "hoc", "altari"]], "antiquo": [1, "manet"], "rata": [1, ","], "sciptio": [1, "legis"], "legis": [[1, 1, 1], ["figurata", "ille", "lator"]], "figurata": [1, ","], "baculi": [[1, 1], ["religio", "."]], "religio": [1, "."], "ergo": [[1, 1, 1, 1, 1, 1, 1, 1, 1, 1, 1, 1], ["ne", "baculator", "quisquis", ",", "manum", "primitus", "cum", "prophetica", "manu", "quia", "sic", "sperneret"]], "res": [1, "occultetur"], "occultetur": [1, ","], "occultum": [1, "reveletur"], "reveletur": [1, ","], "ordinamur": [1, "altius"], "altius": [1, ";"], "nam": [[1, 1, 1, 4, 2, 1, 1, 1, 1, 1, 1, 1, 1, 1, 1], ["id", "quotiens", "ab", "si", "sicut", "cum", "iste", "in", "fulmaro", "semper", "sine", "saepe", "hinc", "mna", "pervertunt"]], "id": [[1, 1, 1], ["de", "ad", "est"]], "quo": [[1, 1, 1, 1, 2, 1, 1, 1, 1, 1], ["dubitatur", "manifeste", "mundi", "celi", "teneam", "plus", "dictum", "me", "feror", ","]], "dubitatur": [1, ","], "scripto": [1, "teste"], "teste": [[1, 1, 1, 1], ["dum", "jordanem", "scitis", "manu"]], "probatur": [1, ","], "creditur": [[1, 1], ["facilius", "invia"]], "facilius": [1, "."], "lignum": [[1, 1, 1, 1, 1], ["per", "figuratur", "sublimatur", "baculista", "largitatem"]], "per": [[1, 1, 1, 1, 1, 3, 1, 1, 1, 1, 6, 1, 1, 1, 1, 1, 2, 1, 1, 1], ["quod", "hoc", "amarum", "dulce", "virtutem", "lignum", "jordanem", "baculum", "defunctum", "giezi", "quos", "hos", "thamar", "singula", "nutus", "ambages", "quem", "viam", "carnis", "diversa"]], "rubrum": [1, "mare"], "mare": [1, "fecit"], "fecit": [1, "tamquam"], "tamquam": [1, "murum"], "murum": [[1, 1], ["stare", ","]], "stare": [1, "legis"], "ille": [[1, 1], ["bajulus", "."]], "bajulus": [1, ","], "figuratur": [1, "quod"], "a": [[1, 1, 1, 1, 1, 1, 1, 1, 1, 1, 1, 1, 1, 1, 1, 1], ["nobis", "foeda", "sanctis", "prelatis", "praesule", "diverticulo", "principibus", "quo", "mente", "christo", "caesare", "longe", "i", "quocumque", "foris", "remotis"]], "nobis": [[1, 1, 1], ["appellatur", "est", "spiritus"]], "appellatur": [1, "tam"], "tam": [[1, 1], ["virga", "caecum"]], "virga": [1, "quam"], "baculus": [2, "."], "siccat": [[1, 1], ["fluctus", "in"]], "fluctus": [[1, 1], ["maris", "avaritiae"]], "maris": [1, ","], "iste": [[1, 1, 1], ["siccat", "dampnat", "grex"]], "avaris": [1, "fluctus"], "avaritiae": [[1, 1], [";", "sunt"]], "mergit": [1, "persequentes"], "persequentes": [1, ","], "dampnat": [[1, 1], ["detrahentes", "maledicos"]], "detrahentes": [1, "morsibus"], "morsibus": [1, "invidiae"], "invidiae": [1, "."], "testatur": [1, "legis"], "lator": [1, ","], "sentiret": [1, "susurrator"], "susurrator": [1, "ebraeorum"], "ebraeorum": [1, "populus"], "populus": [[1, 1], [",", "sitit"]], "expandente": [1, "deo"], "deo": [[1, 1], ["numen", "diffidunt"]], "numen": [[1, 1, 1], ["super", "?", "deitatis"]], "super": [[1, 1], ["aquas", "partes"]], "aquas": [1, "rude"], "rude": [1, "flumen"], "flumen": [[1, 1], ["dulcoravit", ","]], "dulcoravit": [1, "baculus"], "amarum": [1, "parcitatem"], "parcitatem": [1, "et"], "dulce": [[1, 1], ["largitatem", "de"]], "largitatem": [[1, 1], ["denotamus", "designat"]], "denotamus": [1, "singuli"], "singuli": [1, ";"], "ibi": [[1, 1, 1], ["dulce", "serpens", "recubans"]], "amaro": [1, ","], "hic": [[1, 1, 1, 1, 2, 1, 1, 1, 1, 1, 1, 1, 1, 1, 1, 1, 1, 1], ["fit", "per", "tenaces", "vacat", "est", "fulmarus", "vel", "jacent", "et", "relevetur", "tibi", "potus", "vitio", "fraudis", "ambitus", "nostras", "secretum", ","]], "largus": [[1, 1, 1], ["de", "erit", "praeminere"]], "avaro": [1, "per"], "virtutem": [[1, 1], ["baculi", "sequor"]], "ligno": [[1, 1], ["serpens", "?"]], "serpens": [[1, 1], ["elevatus", "adoratur"]], "elevatus": [1, "in"], "deserto": [1, "cruciatus"], "cruciatus": [[1, 1], ["repressit", "hic"]], "repressit": [1, "veneficos"], "veneficos": [1, ";"], "istud": [1, "dignum"], "dignum": [[1, 1], ["largitores", "."]], "largitores": [1, "munit"], "munit": [1, "contra"], "contra": [[1, 1, 1], ["detractores", "nutum", "stimulum"]], "detractores": [1, "et"], "maledicos": [1, "."], "adoratur": [1, ","], "sublimatur": [1, ";"], "notate": [1, "misteria"], "misteria": [1, "hic"], "baculista": [1, "praedicatur"], "praedicatur": [1, "die"], "die": [1, "ista"], "ista": [[1, 1], ["dignus", "sibi"]], "laudis": [1, "gloria"], "gloria": [[1, 1, 1], [".", "macelli", "diffido"]], "jacob": [[1, 1, 1], ["dum", "munus", "rachel"]], "instinctu": [1, "matris"], "matris": [1, "iret"], "iret": [1, "prae"], "prae": [[1, 1, 1, 1, 1], ["timore", "ceteris", "aliis", "caeteris", "omnibus"]], "timore": [1, "fratris"], "fratris": [1, "jungendus"], "jungendus": [1, "avunculo"], "avunculo": [1, ","], "sapienter": [1, "et"], "modeste": [1, "pertransivit"], "pertransivit": [1, "ipso"], "ipso": [1, "teste"], "jordanem": [[1, 1], ["in", "designari"]], "baculo": [[1, 1, 1], [".", ";", "propulit"]], "designari": [1, "potest"], "potest": [[1, 1, 1], ["mundus", "ad", "imbui"]], "notari": [1, "largitas"], "baculum": [[1, 1], [";", "."]], "transit": [1, "ergo"], "baculator": [1, ","], "parcitatis": [1, "supplantator"], "supplantator": [1, ","], "largitate": [1, "saeculum"], "saeculum": [1, "."], "libro": [1, "regum"], "regum": [1, "teste"], "scitis": [1, ","], "pro": [[1, 1, 1, 1, 1, 1, 1, 1], ["nato", "pannis", "vitio", "filiis", "proximo", "israel", "paupere", "trino"]], "nato": [1, "sunamitis"], "sunamitis": [1, "agit"], "agit": [1, "plancum"], "plancum": [1, "querulum"], "querulum": [1, ";"], "elisei": [1, "vice"], "vice": [[1, 1], ["functus", "cotis"]], "functus": [1, "currit"], "currit": [1, "puer"], "puer": [1, ","], "defunctus": [[1, 1], ["nec", "suscitatur"]], "surgit": [1, "ad"], "tenaces": [1, "et"], "avari": [[1, 1, 1], ["per", "fulgor", "vorago"]], "defunctum": [1, "figurari"], "figurari": [1, "recto"], "recto": [1, "possunt"], "possunt": [[1, 1], ["ordine", "enim"]], "ordine": [[1, 1], ["nec", "toto"]], "suscitatur": [2, ","], "avarus": [[1, 1], ["revocatur", ","]], "revocatur": [1, "a"], "foeda": [[1, 1], ["cupidine", "verbis"]], "cupidine": [1, "."], "giezi": [1, "giezitas"], "giezitas": [1, "nota"], "nota": [1, ","], "simonitas": [1, "nuncupat"], "nuncupat": [1, "latinitas"], "latinitas": [1, ","], "quia": [[1, 1, 1, 1, 1, 1, 1, 1, 1, 1, 1, 1, 1, 2, 1, 1], ["per", "largus", "dare", "nequeo", ",", "non", "jejune", "cursitant", "nec", "minus", "juxta", "tota", "sugit", "sic", "placet", "mnas"]], "hos": [[1, 1, 1, 1], ["propagatur", "norunt", "districti", "sorbeat"]], "propagatur": [1, "vix"], "vix": [[1, 1, 1, 1, 1], ["aut", "hi", "aliquem", "ad", "habet"]], "nunquam": [[1, 1, 1], ["largitas", "degustati", "afficit"]], "tegit": [1, "thamar"], "thamar": [[1, 1, 1], ["partes", "probitatem", ","]], "partes": [[1, 1, 1], ["nudas", "quas", "'"]], "nudas": [1, ","], "jungatur": [1, "sibi"], "sibi": [[1, 1, 1, 1, 1, 1, 1], ["judas", "quaerit", "dari", "fari", "consulit", "conscii", "similes"]], "judas": [[1, 1], ["mediante", ","]], "tali": [1, "dono"], "dono": [1, "foederata"], "foederata": [1, "et"], "armilla": [1, "subarrata"], "subarrata": [1, "coit"], "coit": [1, "in"], "propatulo": [1, "."], "xv": [[2, 1, 1, 1, 1, 1, 1], ["si", "parochiam", "quis", "veni", "prudenti", "paucos", "multa"]], "probitatem": [1, "et"], "designat": [1, "moralitas"], "moralitas": [1, ","], "quisquis": [[1, 1, 1], ["largus", "est", "eris"]], "erit": [[1, 1, 2], [",", "ac", "."]], "sociari": [1, "sibi"], "quaerit": [[1, 1, 1], ["thamar", "in", "?"]], "idest": [1, "probitas"], "xvi": [[2, 1, 1, 1, 1, 1, 1], ["set", "clerus", "heu", "me", "stultus", "sanctulum", "alter"]], "figuram": [1, "verto"], "verto": [1, ","], "coivit": [1, "in"], "aperto": [1, "judas"], "latebris": [1, ";"], "praeminere": [1, "cunctis"], "torpere": [1, "non"], "tenebris": [1, "."], "xvii": [[1, 1, 1, 1, 1, 1], ["et", "mundus", "qui", "semper", "magis", "quisquis"]], "condendum": [1, "cordis"], "cordis": [1, "archa"], "fidelis": [[1, 1], ["patriarcha", ","]], "quando": [[1, 1, 1], ["carnes", "cibus", "nec"]], "carnes": [[1, 1, 1, 1], ["abtulit", "suillae", "quam", "cacaborum"]], "abtulit": [1, ","], "quas": [[1, 1], ["incidit", "baculo"]], "incidit": [1, "congregare"], "congregare": [1, "muscas"], "muscas": [1, "vidit"], "vidit": [[1, 1], ["quas", "oculus"]], "propulit": [1, "."], "xviii": [[1, 1, 1, 1, 1, 1], ["in", "quanto", "clamabat", "adde", "si", "exoremus"]], "manifeste": [1, "patet"], "patet": [1, "quod"], "forte": [[1, 1, 1, 1], ["te", "vinceret", "divitiae", "redolet"]], "dilatet": [1, "bacularis"], "bacularis": [1, "largitas"], "cave": [1, "vigilanti"], "vigilanti": [1, "cura"], "defendet": [1, "festi"], "festi": [1, "jura"], "leccatorum": [1, "foeditas"], "foeditas": [1, "."], "xix": [[1, 1, 1, 1, 1, 1], ["possunt", "nullis", "quid", "audi", "set", "exoremus"]], "leccatores": [1, "dici"], "dici": [[1, 1, 1, 1, 1], ["muscae", "prodigi", "debent", "quid", "nazarea"]], "muscae": [1, ","], "mores": [[1, 2, 1, 1], ["muscis", ".", "habet", "redarguis"]], "muscis": [1, "bene"], "bene": [[1, 1, 1, 2], ["consonant", "noverim", "notes", "conveniunt"]], "consonant": [1, "tactu"], "tactu": [1, ","], "voce": [1, "sunt"], "deformes": [1, ","], "hi": [[3, 1, 1], [",", "?", "sunt"]], "sint": [[1, 1], ["enormes", "vel"]], "enormes": [1, ","], "verbis": [[1, 1], ["intonant", "impeteret"]], "intonant": [1, "."], "xx": [[1, 1, 1, 1, 1], ["his", "florebant", "si", "statim", "audi"]], "his": [[1, 1, 1], ["largiri", "extinctae", ","]], "largiri": [1, "non"], "via": [[1, 1, 1, 1, 1], ["largitatis", ".", "non", "creditur", "virtutis"]], "quare": [[1, 1], ["?", "dicit"]], "leccatoribus": [1, "ut"], "sanctis": [1, "perhibetur"], "perhibetur": [1, ","], "idem": [[1, 1, 1], ["erit", "reputant", "laesus"]], "ac": [[1, 1, 1], ["si", "tenero", "peccatis"]], "detur": [1, "victima"], "victima": [1, "daemonibus"], "daemonibus": [1, "."], "xxi": [[1, 1, 1, 1], ["istis", "nescit", "set", "loquitur"]], "istis": [[1, 1], ["loquor", "excipitur"]], "loquor": [[1, 1], ["confidenter", "causa"]], "confidenter": [1, ","], "quis": [[1, 1, 1, 1, 1, 1, 1, 1, 1, 1, 1], ["inpudenter", "iudicet", "sine", "furor", "nunc", "pejeraret", "adulterium", "ferret", "horum", "ergo", "mirreo"]], "inpudenter": [1, "me"], "impeteret": [1, ","], "lacessitus": [1, "reticentem"], "reticentem": [1, ","], "respondentem": [1, ","], "victus": [1, "forte"], "vinceret": [1, "."], "xxii": [[1, 1, 1, 1], ["nam", "axis", "ab", "velut"]], "quotiens": [[1, 1, 1], ["reprobum", "voluit", "fit"]], "reprobum": [1, "reprobo"], "reprobo": [1, "probus"], "probus": [1, "ore"], "ore": [[1, 1, 1], ["lacessit", "psalmos", "resupino"]], "lacessit": [1, ","], "degenerat": [1, "probitas"], "proba": [1, "loquente"], "loquente": [1, "probo"], "probo": [1, ";"], "illos": [[1, 1], ["si", ","]], "aequat": [1, ","], "inquinat": [[1, 1], [",", "egregios"]], "nebulonizat": [1, "cum"], "nebulone": [1, "loquens"], "loquens": [1, "."], "andromachen": [1, "tais"], "tais": [1, ","], "tersites": [1, "hecora"], "hecora": [1, "culpet"], "culpet": [1, ","], "minus": [[1, 1, 1, 1, 1], ["andromache", "hector", "aequo", "est", "aptus"]], "andromache": [1, ","], "hector": [1, "erit"], "inclament": [1, "igitur"], "igitur": [[1, 1, 1, 1, 1, 1], ["furem", "hec", "haec", "censorinus", "consilio", "summum"]], "furem": [1, ","], "paticum": [1, ","], "parasitum": [1, ","], "obiciam": [1, ","], "quidlibet": [1, "esse"], "fero": [1, "."], "stulti": [1, "cum"], "prudentibus": [1, "currunt"], "currunt": [1, "ad"], "coronam": [2, ","], "juvenalis": [[1, 1], ["autumnant", "extitit"]], "autumnant": [1, "sumere"], "sumere": [1, "personam"], "personam": [2, ";"], "noverim": [1, "pallada"], "pallada": [1, "patronam"], "patronam": [1, ","], "semper": [[2, 1, 1, 1, 1, 1, 1, 1, 1, 1, 1], ["ego", "nocuit", "arescit", "agitant", "cornicantur", "multum", "habet", "negligat", "esse", "est", "perfrui"]], "ego": [[2, 1, 1], ["auditor", "magis", "dixi"]], "auditor": [2, "tantum"], "tantum": [[2, 1, 1, 1, 1], [",", "habet", "pauperibus", "gloriantur", "relucentes"]], "nunquamne": [2, "reponam"], "reponam": [2, "?"], "cibus": [1, "deficit"], "deficit": [[1, 1], ["animabus", "et"]], "animabus": [1, "brutis"], "brutis": [1, ","], "mugiendo": [1, "postulant"], "postulant": [1, "cibum"], "cibum": [1, "suae"], "suae": [2, "salutis"], "salutis": [2, ";"], "resonans": [1, "vocibus"], "vocibus": [1, "argutis"], "argutis": [1, "fistula"], "fistula": [1, "disparibus"], "disparibus": [1, "septem"], "septem": [1, "compacta"], "compacta": [1, "cicutis"], "cicutis": [1, "."], "festis": [1, "bacularibus"], "bacularibus": [1, "interesse"], "interesse": [[1, 1], ["minimus", "poterit"]], "minimus": [1, "volo"], "volo": [1, ","], "nequeo": [1, "magnus"], "magnus": [[1, 1], [",", "eris"]], "major": [1, ","], "maximus": [1, ";"], "derogare": [1, "vitiis"], "vitiis": [[1, 1], ["omnibus", "sepulta"]], "animus": [1, ","], "nos": [[1, 1, 1], ["ergo", "aeternitas", "mordes"]], "manum": [1, "ferulae"], "ferulae": [1, "subduximus"], "subduximus": [1, "."], "videam": [1, "reprobos"], "reprobos": [1, "opibus"], "affluere": [1, ","], "dominari": [1, "vitia"], "vitia": [[1, 1, 1], [",", "quis", "delebo"]], "virtutes": [[1, 1], ["succumbere", "appetit"]], "succumbere": [1, ","], "vilipendi": [1, "faeminas"], "faeminas": [1, ","], "viros": [[1, 1], ["autem", ","]], "nubere": [1, ","], "difficile": [1, "nobis"], "satiram": [1, "non"], "scribere": [[1, 1], [".", "zelus"]], "spargat": [1, "ergo"], "clio": [1, "jacula"], "jacula": [[1, 1], ["in", ","]], "operit": [1, "pastoralis"], "pastoralis": [[1, 1], ["infula", "sedes"]], "infula": [1, ";"], "illis": [1, "omnibus"], "irem": [1, "per"], "singula": [[1, 1], ["?", "singulis"]], "defluit": [1, "in"], "subditos": [1, "vitiorum"], "vitiorum": [[1, 1, 1], ["macula", "rivi", "seges"]], "macula": [[1, 1], [".", "feminas"]], "ecce": [[1, 1], ["sponsi", "papas"]], "sponsi": [[1, 1], ["comites", ","]], "comites": [1, "vendunt"], "sponsae": [[1, 1], ["dotes", "dos"]], "dotes": [1, ","], "furantur": [[1, 1], ["in", "fuscinis"]], "cacabo": [1, "carnem"], "carnem": [1, "sacerdotes"], "sacerdotes": [1, "."], "spectes": [1, "medullitus"], "medullitus": [1, ","], "rem": [[1, 2], ["bene", ","]], "notes": [1, ","], "christum": [[1, 1, 1], ["vendunt", "praefigurat", "a"]], "novi": [1, "scariotes"], "scariotes": [1, "."], "prorsus": [[1, 1], ["obsolvit", "sperni"]], "obsolvit": [1, "usus"], "usus": [1, "largiendi"], "largiendi": [1, "praebendas"], "praebendas": [1, ","], "altaria": [1, ","], "solent": [1, "vendi"], "vendi": [1, ";"], "versa": [1, "est"], "habitum": [[1, 1], [",", "verterunt"]], "cupido": [[1, 1], ["tenendi", ";"]], "tenendi": [1, ";"], "temprore": [1, "crevit"], "crevit": [1, "amor"], "amor": [[1, 1], [",", "nummi"]], "summus": [1, ","], "habendi": [1, "."], "studet": [1, "praesul"], "praesul": [[1, 1, 1], ["pretiis", ",", "ducit"]], "pretiis": [1, "et"], "archilevita": [1, ","], "vivens": [1, "solitarius"], "solitarius": [1, "coenat"], "coenat": [1, "heremita"], "heremita": [1, "."], "morerentur": [1, "utinam"], "utinam": [1, "hi"], "vivunt": [1, "ita"], "ita": [[1, 1], ["!", "de"]], "felices": [1, "obeunt"], "obeunt": [1, ","], "crimine": [1, "vita"], "vis": [[1, 1, 2], ["decanus", "libidinis", "esse"]], "decanus": [1, "fieri"], "fieri": [[1, 1, 1, 1], [",", "doctores", "noles", "sub"]], "auri": [[1, 1], ["multa", "possessores"]], "multa": [[1, 1, 1], ["tibi", "?", "ferunt"]], "tibi": [[1, 1], ["sit", "precipue"]], "argenti": [1, "marca"], "fidei": [1, "teste"], "manu": [[1, 1, 1, 1], ["parca", "fulgurat", "fulgens", "dapsili"]], "quisque": [[1, 1], ["sua", "nititur"]], "nummorum": [[1, 1], ["servat", "congeriem"]], "servat": [1, "in"], "arca": [1, "."], "climate": [1, ","], "celi": [1, "signo"], "signo": [[1, 1], ["est", "vel"]], "abbas": [1, "vel"], "pontifex": [[1, 1, 3, 1], ["pectore", "libellum", ",", "nichil"]], "pectore": [1, "benigno"], "benigno": [1, ","], "nuptiis": [1, ","], "vitae": [[1, 1, 1, 1], ["ligno", "desperatis", "disconvenit", "precedentium"]], "rara": [1, "avis"], "avis": [1, "in"], "terris": [1, "nigroque"], "nigroque": [1, "simillima"], "simillima": [1, "cigno"], "cigno": [1, "!"], "judaeis": [1, "odio"], "odio": [1, "sunt"], "suillae": [1, ","], "extinctae": [1, "sunt"], "virtutum": [[1, 1, 1], ["scintillae", "probitas", "."]], "scintillae": [1, "hic"], "vacat": [1, "libidini"], "libidini": [1, ","], "gulae": [1, "servit"], "servit": [1, "ille"], "credite": [1, "me"], "vobis": [[1, 1], ["folium", "hunc"]], "folium": [1, "recitare"], "recitare": [1, "sibillae"], "sibillae": [1, "."], "mentibus": [1, "imbutis"], "imbutis": [1, "in"], "nummo": [[1, 1, 1], ["constituunt", "deditus", "careas"]], "constituunt": [1, "spem"], "spem": [1, "suae"], "nolunt": [[1, 1], ["dici", "se"]], "prodigi": [1, "rebus"], "dissolutis": [1, ";"], "fallit": [[1, 1], ["enim", "ymago"]], "vitium": [[1, 1, 1, 1], ["specie", "derives", "peccant", ","]], "prelatis": [1, "defluunt"], "defluunt": [1, "vitiorum"], "rivi": [1, ","], "pauperibus": [1, "irascuntur"], "irascuntur": [1, "divi"], "divi": [1, ";"], "impletur": [1, "versiculus"], "versiculus": [1, "illius"], "illius": [[1, 1], ["lascivi", "johannis"]], "lascivi": [1, "quidquid"], "quidquid": [[1, 1, 1], ["delirant", "talis", "lustrat"]], "delirant": [1, "reges"], "plectuntur": [1, "achivi"], "achivi": [1, "."], "vos": [[1, 2], ["ergo", "detineam"]], "talia": [1, ","], "agatis": [1, ","], "futurae": [[1, 1], ["gaudio", "gloriae"]], "gaudio": [1, "vitae"], "desperatis": [1, "illudque"], "illudque": [1, "lucanicum"], "lucanicum": [1, "mente"], "pertractatis": [1, "tolle"], "tolle": [1, "moras"], "moras": [[1, 1], [",", "si"]], "nocuit": [2, "differre"], "differre": [2, "paratis"], "paratis": [[1, 1], [".", "?"]], "parochiam": [1, "contrahit"], "contrahit": [1, "lege"], "matrimonii": [1, "sacerdos"], "sacerdos": [[1, 1], ["a", "ut"]], "praesule": [1, ","], "nummi": [[1, 3], ["sunt", ","]], "medii": [1, ","], "tumor": [1, "marsupii"], "marsupii": [1, ","], "dabit": [1, "ei"], "ei": [[1, 1], ["pontifex", ","]], "libellum": [1, "repudii"], "repudii": [1, "."], "neque": [[1, 1], ["presbiteros", "labra"]], "presbiteros": [1, "decet"], "decet": [[1, 1, 1], ["excusari", "propriisque", "sanctitudo"]], "excusari": [1, ","], "suis": [1, "ovibus"], "ovibus": [1, "constat"], "constat": [1, "inquinari"], "inquinari": [1, ","], "quosdam": [1, "contigit"], "contigit": [1, "vel"], "ementulari": [1, "vel"], "perimi": [1, ","], "voluit": [[1, 1], ["fortuna", "carere"]], "fortuna": [1, "iocari"], "iocari": [1, "."], "deditus": [1, "sequitur"], "hunc": [[1, 1, 1, 2, 1, 1, 1], ["morem", "praestat", "a", "jure", "futurae", "plane", "ad"]], "morem": [1, ","], "tanto": [[1, 1], ["quis", "magis"]], "iudicet": [1, "quemque"], "quemque": [[1, 1], ["digniorem", "decet"]], "digniorem": [1, ","], "illum": [1, "quanto"], "quanto": [[1, 1, 1, 1], ["noverit", "plura", "plus", "marsupio"]], "noverit": [[1, 1], ["esse", "ista"]], "ditiorem": [1, "o"], "praestat": [1, "honorem"], "honorem": [1, "!"], "plura": [1, "possidet"], "possidet": [2, ","], "plus": [[1, 1, 1, 1], ["ditescit", "infuderis", "equo", "cunctis"]], "ditescit": [1, ","], "locuples": [2, ","], "sitit": [[1, 1], ["et", "ante"]], "ardescit": [1, ";"], "sicut": [[1, 1, 1, 1], ["ydropicus", "exprimunt", "oracii", "vestimentum"]], "ydropicus": [1, ","], "arescit": [1, ","], "crescit": [[1, 1, 1, 1], ["amor", ".", ",", "et"]], "ipsa": [1, "pecunia"], "pecunia": [[1, 2, 1], ["crescit", "primum", "donat"]], "nullis": [1, "avaritia"], "erubescit": [1, ","], "ex": [[1, 1, 1, 1, 1, 1], ["hac", "ipsis", "rapto", "toto", "iis", "denario"]], "hac": [1, "vis"], "libidinis": [1, "derivata"], "derivata": [1, "crescit"], "semel": [1, "opibus"], "dives": [[1, 1, 1], ["intumescit", ".", "fieri"]], "intumescit": [[1, 1], [",", ";"]], "ingujnis": [1, "et"], "capitis": [1, "que"], "que": [[1, 1, 1, 1, 1], ["sunt", "solet", "video", "cecidi", "prosunt"]], "discrimina": [1, "nescit"], "nescit": [[1, 1, 1], [".", "mundus", "condolere"]], "florebant": [1, "antiquitus"], "doctores": [3, ","], "acquirunt": [1, "redditus"], "possessores": [1, ","], "exprimunt": [1, "versibus"], "versibus": [1, "auctores"], "auctores": [[1, 1], [",", "inquinat"]], "dat": [1, "census"], "census": [1, "honores"], "honores": [1, "."], "compati": [1, ","], "condolere": [1, "mendicanti"], "mendicanti": [1, "palladi"], "palladi": [1, ","], "solet": [[1, 1], ["vigere", "esse"]], "vigere": [1, ","], "careas": [1, ","], "foras": [[2, 1], ["expellere", "."]], "expellere": [2, ","], "ipse": [[2, 1, 1], ["licet", "docebo", "veni"]], "venias": [2, "musis"], "musis": [2, "comitatus"], "comitatus": [[2, 1], [",", "intrat"]], "homere": [[2, 1, 1], [".", "foras", "\"."]], "axis": [1, "magisterii"], "magisterii": [1, "fractus"], "fractus": [1, "est"], "temo": [1, ","], "audiri": [1, "si"], "cupiam": [1, ","], "auditores": [1, "emo"], "emo": [1, ";"], "conqueror": [1, ","], "gemo": [1, "scire"], "scire": [[1, 1], ["volunt", "quam"]], "volunt": [[1, 1], ["omnes", "palacii"]], "mercedem": [1, "solvere"], "solvere": [1, "nemo"], "xxiii": [[1, 1, 1], ["senes", "mos", "stultus"]], "senes": [[1, 1], ["avaritiae", ","]], "imbuti": [1, "felle"], "felle": [1, ","], "odor": [1, "lucri"], "lucri": [[1, 1], ["pueris", "voto"]], "pueris": [1, "dulcior"], "dulcior": [1, "est"], "melle": [1, ";"], "nolle": [1, "pudicitiam"], "pudicitiam": [1, ","], "nummos": [1, "autem"], "velle": [1, ","], "ante": [[1, 1], ["alpha", "flumen"]], "alpha": [1, "et"], "beta": [1, "puellae"], "puellae": [1, "."], "xxiv": [[1, 1, 1], ["si", "ergo", "exultans"]], "recte": [1, "de"], "derives": [1, ","], "gestis": [1, "consulas"], "consulas": [1, "athenarum"], "athenarum": [1, "cives"], "cives": [6, ","], "inter": [[1, 1, 1, 1, 1, 1], ["actus", "haedos", "socraticos", "avidos", "utrumque", "curas"]], "actus": [1, "saeculi"], "saeculi": [1, "pravos"], "pravos": [1, "et"], "declives": [1, "intolerabilius"], "intolerabilius": [1, "nichil"], "faemina": [[1, 1], ["dives", "limen"]], "xxv": [[1, 1, 1], ["hoc", "divites", "quisquis"]], "idcirco": [[1, 1], ["dixerim", "divitias"]], "dixerim": [1, ","], "feminas": [1, "existimet"], "existimet": [1, ","], "quarum": [1, "linguae"], "linguae": [1, "jacula"], "fascinantes": [1, "oculi"], "oculi": [1, ","], "digita": [1, "novacula"], "novacula": [1, "."], "diverticulo": [1, "repetatur"], "repetatur": [1, "fabula"], "fabula": [1, "."], "xxvi": [[1, 1, 1], ["filii", "cum", "poenas"]], "filii": [1, "nobilium"], "nobilium": [1, "dum"], "juniores": [1, ","], "mittuntur": [1, "in"], "franciam": [1, "fieri"], "prece": [1, "vel"], "domant": [1, "corruptores"], "corruptores": [1, ";"], "praetextatos": [1, "referunt"], "referunt": [1, "artaxata"], "artaxata": [1, "mores"], "xxvii": [[1, 1], ["mores", "de"]], "barbaris": [1, ","], "latinus": [1, "et"], "grecus": [1, ","], "plebs": [[1, 1], ["est", "aebrea"]], "caecum": [[1, 1], ["ducit", "ut"]], "ducit": [[1, 1], ["caecus", "carum"]], "caecus": [1, ","], "se": [[1, 1, 1, 1, 1, 1, 1, 1, 1, 1], ["mares", "locus", "prebet", "credit", "quemque", "diu", "'", "pro", "vestem", "quantum"]], "mares": [1, "effaeminant"], "effaeminant": [1, "et"], "equa": [1, "fit"], "equus": [1, ","], "expectes": [1, "ab"], "homine": [1, "hoc"], "usque": [1, "ad"], "pecus": [1, "."], "xxviii": [1, "et"], "metuunt": [1, "animae"], "animae": [1, "discrimen"], "discrimen": [1, ","], "principes": [1, "in"], "verterunt": [1, "hoc"], "crimen": [1, ","], "virum": [1, "viro"], "viro": [1, "turpiter"], "turpiter": [[1, 1, 1], ["jungit", ",", "nos"]], "jungit": [1, "novus"], "novus": [1, "hymen"], "hymen": [1, ","], "exagitata": [1, "procul"], "xxix": [1, "unum"], "unum": [[1, 1], ["est", "duo"]], "ceteris": [1, ","], "cuncti": [1, "mirantur"], "mirantur": [1, ","], "largi": [1, "sunt"], "numquam": [1, "ditantur"], "ditantur": [1, ";"], "divitiae": [1, "largis"], "largis": [1, "sociantur"], "sociantur": [1, ","], "conveniunt": [2, "nec"], "una": [[2, 1], ["sede", "ne"]], "sede": [2, "morantur"], "morantur": [2, "."], "xxx": [1, "esto"], "esto": [[1, 1], ["fur", "cato"]], "fur": [1, "vel"], "proditor": [1, ","], "verres": [1, "sive"], "sive": [[1, 1], ["graccus", "lia"]], "graccus": [1, ","], "reputaberis": [1, "ut"], "thebarum": [1, "baccus"], "baccus": [1, ";"], "cato": [[1, 1], ["moribus", "eructat"]], "moribus": [[1, 1], [",", "ultima"]], "scientia": [[1, 1, 1], ["flaccus", "tantum", "respuunt"]], "flaccus": [1, "duceris"], "duceris": [1, "planta"], "planta": [1, "velud"], "velud": [1, "ictus"], "ictus": [1, "ab"], "hercule": [1, "cacus"], "cacus": [1, "."], "multiformis": [1, "hominum"], "hominum": [[1, 1, 1], ["fraus", "canone", "curis"]], "fraus": [1, "et"], "injustitia": [1, ","], "letalis": [1, "ambitio"], "ambitio": [1, ","], "furtum": [1, ","], "lenocinia": [1, "cogunt"], "cogunt": [1, ","], "ordiar": [1, "conversus"], "conversus": [1, "ad"], "furor": [1, ","], "tanta": [1, "licentia"], "licentia": [1, "?"], "luxus": [[1, 1], [",", "et"]], "macelli": [1, ","], "infamis": [1, "concubitus"], "concubitus": [1, "patrantis"], "patrantis": [1, "ocelli"], "ocelli": [1, ","], "quicquid": [1, "agunt"], "agunt": [1, "homines"], "homines": [[1, 1], ["animo", "ad"]], "animo": [[1, 1], ["rebelli", "consultus"]], "rebelli": [1, ","], "gaudia": [[1, 1], [",", "voto"]], "discursus": [1, "nostri"], "nostri": [1, "farrago"], "farrago": [1, "libelli"], "libelli": [1, "."], "tot": [[1, 1, 1, 1, 1], ["sordes", "tumultus", "inmutant", "assumunt", "plagis"]], "sordes": [[1, 1], ["luxuriae", "."]], "luxuriae": [1, ","], "tumultus": [[1, 1], ["tot", ","]], "inmutant": [1, "species"], "species": [1, ","], "assumunt": [1, "cultus"], "cultus": [1, ","], "dicat": [1, "aliquis"], "aliquis": [[1, 1, 1, 1], ["animo", "dente", ",", "'"]], "consultus": [1, "'"], "'": [[1, 1, 1, 1, 1, 1], ["quo", "iv", "heu", "turpiter", "set", "non"]], "teneam": [2, "nodo"], "nodo": [2, "mutantem"], "mutantem": [2, "prothea"], "prothea": [2, "vultus"], "vultus": [2, "?"], "mundum": [[1, 1, 1], ["intuear", "male", "guerrae"]], "intuear": [1, "sordis"], "sordis": [[1, 1], ["fluxu", "fex"]], "fluxu": [1, "mersum"], "mersum": [1, "et"], "ordinem": [1, "perversum"], "perversum": [1, "et"], "principibus": [1, "in"], "vulgus": [1, "dispersum"], "dispersum": [1, "si"], "negat": [2, ","], "facit": [1, "indignatio"], "indignatio": [1, "versum"], "versum": [1, "."], "primis": [[1, 1], ["pontifices", "requiritur"]], "prelatos": [1, "noto"], "noto": [[1, 1], [",", "'."]], "grex": [[1, 1], ["hominum", "solet"]], "canone": [1, "remoto"], "remoto": [[1, 1], ["totus", ","]], "poculis": [1, ","], "voto": [[1, 1], ["estuat", "."]], "estuat": [1, "et"], "disconvenit": [1, "ordine"], "toto": [[1, 1], [".", ","]], "heu": [[1, 1, 1, 1], ["quam", "mentes", "quid", ","]], "nugatorii": [1, "praesules"], "moderni": [[1, 1, 1, 1], ["!", "regni", "?", "praesules"]], "debent": [1, "potius"], "praetores": [1, "averni"], "averni": [[1, 2], ["vel", "."]], "spretores": [1, "melius"], "melius": [1, "judicis"], "judicis": [[2, 1], ["aeterni", "opprimet"]], "aeterni": [2, "."], "potores": [1, "bibuli"], "bibuli": [1, "media"], "media": [1, "de"], "nocte": [1, "falerni"], "falerni": [1, "."], "dic": [[1, 1], ["papa", "pontifex"]], "spes": [[1, 1], ["sponsi", "est"]], "dos": [1, ","], "redarguis": [1, "et"], "sermones": [1, "foedos"], "foedos": [1, ","], "pejor": [1, "pessimis"], "pessimis": [2, ","], "haedus": [1, "inter"], "haedos": [1, ","], "socraticos": [1, "notissima"], "notissima": [1, "fossa"], "fossa": [1, "cinedos"], "cinedos": [1, "!"], "datis": [1, "opibus"], "tumorem": [1, "crescit"], "infuderis": [1, ","], "oracii": [1, "versus"], "versus": [[1, 1, 1], ["innotescit", "dum", "."]], "innotescit": [1, ","], "sincerum": [1, "nisi"], "vas": [1, ","], "quodcumque": [[1, 1], ["infundis", "juvaret"]], "infundis": [1, ","], "acescit": [1, "."], "nuptias": [[1, 1], ["contra", "hoste"]], "nutum": [1, "dei"], "dei": [[2, 1, 1, 1], [",", ".", "\"", "violat"]], "pervertit": [1, "judicium"], "judicium": [[1, 1], [",", "judicis"]], "fovet": [1, "partem"], "partem": [[1, 1], ["rei", "eligit"]], "rei": [[2, 2, 1], [".", ",", "reos"]], "pretiosa": [1, "quaelibet"], "quaelibet": [1, "famulantur"], "famulantur": [1, "ei"], "india": [1, "mittit"], "mittit": [1, "ebur"], "ebur": [1, ","], "molles": [1, "sua"], "thura": [1, "sabei"], "sabei": [1, "."], "metit": [1, "omnia"], "omnia": [1, "quadam"], "quadam": [1, "falce"], "falce": [1, "manuum"], "manuum": [1, ","], "accipit": [1, "ab"], "nulli": [[1, 1], ["reddit", "potest"]], "reddit": [[1, 1], ["mutuum", "inconsultas"]], "mutuum": [1, ";"], "sonuit": [1, "illud"], "illud": [[1, 1], ["non", "est"]], "ambiguum": [1, ";"], "alterius": [1, "siccas"], "siccas": [1, "pocula"], "pocula": [1, ","], "tuum": [1, "."], "eligendi": [1, "praesulis"], "praesulis": [1, "quotiens"], "requiritur": [1, ","], "marsupio": [1, "interesse"], "poterit": [[1, 1], ["romano", "retinere"]], "romano": [1, "concilio"], "concilio": [1, ","], "ultima": [[1, 1], ["fit", "."]], "questio": [1, "."], "proh": [1, "si"], "scires": [1, ","], "quanta": [1, "sit"], "vanitas": [[1, 1, 1], ["claustralium", "colorat", "mundi"]], "claustralium": [1, ","], "duri": [1, ","], "dispares": [1, "vitae"], "precedentium": [1, "!"], "ipsis": [1, "conjiceres"], "conjiceres": [1, "finem"], "finem": [[1, 1], ["rerum", "teneri"]], "rerum": [1, "omnium"], "omnium": [[2, 1], [",", "vitio"]], "quoniam": [[1, 1], ["jam", "scriptitat"]], "caritas": [1, "refrigescit"], "refrigescit": [1, "plurium"], "plurium": [1, "."], "coenobita": [1, "quilibet"], "quilibet": [1, "vivit"], "vivit": [[1, 1, 1], ["dissolutus", "non", "?"]], "dissolutus": [1, ","], "effrons": [1, ","], "loquitur": [[1, 1], ["signo", "sublimia"]], "nutus": [1, ";"], "claustris": [1, ","], "ubi": [[1, 1], ["grex", "sunt"]], "mutus": [1, ","], "vivitur": [1, "ex"], "rapto": [1, ","], "hospes": [1, "ab"], "hospite": [1, "tutus"], "tutus": [1, "."], "equo": [1, "satagit"], "satagit": [1, "martha"], "martha": [1, "sive"], "lia": [1, ","], "aequo": [1, "nititur"], "nititur": [[1, 1], ["rachel", "vendere"]], "rachel": [[1, 1], ["et", "fugiens"]], "maria": [1, ";"], "nulla": [[1, 1], ["partem", "via"]], "eligit": [1, "meliorem"], "meliorem": [1, ","], "jejune": [1, "deficiunt"], "deficiunt": [1, "pariter"], "pariter": [[1, 2], ["in", "et"]], "imitator": [1, "est"], "johannis": [1, ","], "tegimen": [1, "cameli"], "cameli": [1, "pro"], "pannis": [1, ","], "epulum": [1, "silvestre"], "silvestre": [1, "mel"], "mel": [[1, 1], [",", "quia"]], "potus": [[1, 1], ["purus", ","]], "purus": [1, "amnis"], "amnis": [1, "?"], "laudamus": [1, "veteres"], "nostris": [1, "utimur"], "utimur": [1, "annis"], "annis": [1, "."], "clerus": [1, ","], "sors": [1, "domini"], "domini": [[1, 1, 1, 1], ["vocati", "mandatum", "prudens", "fit"]], "vocati": [1, "deberet"], "deberet": [1, ","], "cui": [[1, 1, 1], ["precipue", "adhereas", "debeam"]], "precipue": [[1, 1], ["sordis", "sit"]], "fex": [1, "adhaeret"], "adhaeret": [1, ";"], "vox": [1, "ergo"], "prophetica": [1, "locum"], "haberet": [1, ";"], "omne": [[1, 1, 1, 1], ["caput", "cor", "superbum", "solum"]], "caput": [[1, 1], ["languidum", "mundi"]], "languidum": [1, "et"], "cor": [[1, 1, 1], ["maeret", "indurat", "habens"]], "maeret": [1, "."], "ecclesiam": [[1, 1], ["vendunt", "in"]], "mercantur": [1, "?"], "fornicarii": [1, ","], "mechantur": [1, ","], "naturam": [1, "transvolant"], "transvolant": [1, "et"], "abhominantur": [1, "?"], "clerici": [1, ","], "exempla": [1, "petantur"], "petantur": [1, "."], "clamabat": [1, "decalogus"], "decalogus": [1, ","], "pejeraret": [1, ","], "adulterium": [1, "furtumve"], "furtumve": [1, "patraret"], "patraret": [1, ","], "naso": [1, "prevalet"], "prevalet": [1, ","], "dictum": [1, "claret"], "claret": [1, "jupiter"], "jupiter": [1, "esse"], "pium": [1, "statuit"], "statuit": [1, ","], "juvaret": [1, "."], "mirum": [1, ","], "tendimus": [[1, 1], ["homines", "huc"]], "imum": [[1, 1], ["?", ","]], "humus": [1, "humum"], "humum": [1, "sapere"], "sapere": [1, "debet"], "limus": [1, "limum"], "limum": [[1, 1], [".", ";"]], "imitemur": [2, "igitur"], "hec": [1, "dicentem"], "dicentem": [2, "mimum"], "mimum": [[1, 1], ["o", ";"]], "quaerenda": [2, "pecunia"], "primum": [2, "."], "gratum": [1, "et"], "benignum": [1, "et"], "ferre": [1, "prae"], "aliis": [[1, 1], ["triumphale", "tu"]], "triumphale": [1, "signum"], "signum": [1, ","], "opus": [1, "fac"], "fac": [[1, 1], ["malignum", "parisius"]], "malignum": [1, ","], "aude": [1, "aliquid"], "aliquid": [1, "brevibus"], "brevibus": [1, "giaris"], "giaris": [1, "et"], "carcere": [1, "dignum"], "detineam": [[1, 1], ["per", "turbine"]], "ambages": [1, "multas"], "multas": [1, ","], "mentes": [[1, 1, 1, 1], ["omnium", "perditae", "reducite", ";"]], "sepultas": [1, "demolitur"], "demolitur": [1, ","], "allicit": [[1, 1], [",", "cutis"]], "inconsultas": [1, "ambitus"], "ambitus": [[1, 1, 1], ["et", ",", "nodos"]], "opum": [1, "metuenda"], "metuenda": [1, "faculatas"], "faculatas": [1, "."], "excipitur": [1, "solus"], "solus": [[1, 1], ["hic", "inter"]], "fulmarus": [1, ","], "larga": [1, "manu"], "fulgurat": [1, ","], "genere": [1, "praeclarus"], "praeclarus": [1, ";"], "avidos": [1, "vivit"], "inde": [[1, 1], ["manu", "primo"]], "fulgens": [1, "vel"], "fulgor": [1, "amarus"], "amarus": [1, "."], "mos": [1, "fulmari"], "fulmari": [1, "praecipit"], "praecipit": [1, "locum"], "vago": [1, ","], "fulmaro": [1, "displicet"], "displicet": [1, "avari"], "vorago": [1, ";"], "fulmarum": [1, "largificat"], "largificat": [1, "nobilis"], "nobilis": [2, "propago"], "propago": [[1, 1], [",", "?"]], "genus": [[1, 1], ["arguitur", "et"]], "arguitur": [1, "vultu"], "vultu": [1, ","], "ymago": [1, "."], "dapsili": [1, "fulgurans"], "fulgurans": [1, ","], "fulmare": [1, ","], "permittas": [1, "peditem"], "peditem": [1, "me"], "repatriare": [1, "."], "eris": [2, ","], "bipedem": [1, "scis"], "scis": [1, "quadrupedare"], "quadrupedare": [1, "."], "divites": [1, "in"], "dissoluti": [1, "tanquam"], "tanquam": [1, "idem"], "reputant": [1, "uti"], "uti": [[1, 2], ["vel", ","]], "abuti": [1, ";"], "hii": [1, "sunt"], "intima": [1, "non"], "respondent": [1, "cuti"], "cuti": [1, ","], "agitant": [1, "nunc"], "virtute": [[1, 1, 1], ["locuti", "multa", ","]], "locuti": [1, "."], "locus": [1, "obtulit"], "obtulit": [1, ","], "ocultis": [1, "vacent"], "vacent": [1, ","], "tractant": [1, "de"], "taydibus": [1, ","], "sabinis": [1, "tacent"], "tacent": [1, ";"], "latenter": [1, "hic"], "haec": [[1, 1, 1, 1, 1, 1, 1, 1], ["vel", "et", "cupido", "dicentem", "est", "genesis", "ultima", "consuetudo"]], "carnis": [[1, 1], ["ad", "vitium"]], "officium": [[1, 1], ["carnea", "nil"]], "carnea": [1, "membra"], "membra": [1, "placent"], "placent": [1, "."], "futura": [1, "divitum"], "divitum": [1, "gloria"], "diffido": [1, ","], "mortem": [1, "vulnerat"], "vulnerat": [1, "hic"], "secreto": [1, "lusitant"], "lusitant": [1, "aeneas"], "aeneas": [1, "et"], "dido": [1, ","], "irruit": [2, "in"], "vetitum": [[1, 1], ["dampni", "cupimus"]], "dampni": [1, "secura"], "libido": [1, "."], "missus": [1, "sum"], "sum": [[1, 1], ["in", "pneumate"]], "vineam": [[1, 1], ["circa", "amodo"]], "circa": [1, "horam"], "horam": [[1, 1], ["nonam", "mortis"]], "nonam": [1, ","], "suam": [[1, 1], ["quisque", "christus"]], "vendere": [1, "personam"], "cursitant": [1, "omnes"], "rithmis": [1, "dum"], "lascivio": [1, "versus"], "propino": [1, ","], "rodit": [[1, 1], ["forsan", ";"]], "forsan": [[1, 1, 1], ["aliquis", "non", "adiunt"]], "dente": [1, "me"], "canino": [1, ","], "afflatus": [1, "sum"], "pneumate": [1, "divino"], "divino": [1, "neque"], "labra": [1, "prolui"], "prolui": [1, "fonte"], "fonte": [[1, 1], ["caballino", "litterarum"]], "caballino": [1, "."], "proferam": [1, "verba"], "verba": [[1, 1], ["parum", "palato"]], "parum": [[1, 1, 1], ["culta", "possidet", ","]], "culta": [1, "et"], "prodeant": [1, "satis"], "satis": [1, "inconsulta"], "inconsulta": [1, "."], "aenigmatica": [1, "non"], "occulta": [1, ","], "quodam": [2, "prodire"], "prodire": [2, "tenus"], "tenus": [2, ","], "ultra": [[2, 1], [".", "promissum"]], "vestigia": [2, "veterum"], "veterum": [[1, 1], ["refutem", "moderni"]], "refutem": [1, ","], "adipisci": [1, "rimulis"], "rimulis": [1, "corporis"], "corporis": [1, "salutem"], "salutem": [1, ","], "impleri": [1, "divitiis"], "divitiis": [[1, 1], ["et", "vita"]], "curare": [1, "cutem"], "cutem": [1, "?"], "decuit": [1, "magnos"], "magnos": [1, ","], "turpe": [1, "putem"], "putem": [1, "?"], "appetit": [1, ","], "labitur": [1, "in"], "quaerens": [1, "sapientiam"], "sapientiam": [1, "irruit"], "sinodis": [1, "confidendo"], "confidendo": [1, "tonat"], "tonat": [1, ","], "electionibus": [1, "prima"], "prima": [1, "grande"], "grande": [[1, 1], ["sonat", "loqui"]], "sonat": [1, ";"], "intronizat": [1, "praesules"], "dites": [1, "impersonat"], "impersonat": [1, "et"], "formam": [1, "regina"], "regina": [1, "pecunia"], "donat": [1, "."], "adora": [1, "pecuniam"], "pecuniam": [1, ","], "deos": [[1, 1], ["adoras", ","]], "adoras": [1, "cur"], "struis": [1, "armaria"], "armaria": [1, ","], "libros": [1, "honoras"], "honoras": [1, "?"], "longas": [1, "fac"], "parisius": [1, "vel"], "athenis": [1, "moras"], "attuleris": [2, ","], "ibis": [[1, 1], [",", "."]], "disputet": [1, "philosophus"], "philosophus": [1, "vacuo"], "vacuo": [1, "cratere"], "cratere": [1, ","], "sciat": [[1, 1], [",", "artes"]], "habere": [1, ";"], "pauper": [[1, 1, 1, 1], ["fueris", "et", "diogenes", "omnis"]], "fueris": [1, ","], "auctorum": [1, "plenus"], "plenus": [1, ","], "prodest": [2, ","], "vixerit": [1, "pauper"], "egenus": [1, "?"], "illinc": [[1, 1], ["cogit", "me"]], "cogit": [[1, 1], ["nuditas", "scribere"]], "nuditas": [1, "vacuumque"], "vacuumque": [1, "penus"], "penus": [1, ","], "usura": [1, "vorax"], "vorax": [1, "avidumque"], "avidumque": [1, "in"], "tempore": [[1, 1], ["fenus", ","]], "fenus": [1, "."], "joseph": [1, "in"], "vinculis": [1, "christum"], "praefigurat": [1, ","], "plagis": [1, "pharao"], "pharao": [1, "durum"], "durum": [[1, 1, 1], ["cor", "publicae", "."]], "indurat": [1, ","], "filiis": [2, "israel"], "israel": [[1, 1, 1, 1], ["exitus", "afferre", "manibus", ";"]], "exitus": [[1, 1, 1], ["obturat", "acta", "magnis"]], "obturat": [1, "quid"], "valet": [1, "haec"], "genesis": [1, ","], "paupertas": [[1, 1, 1], ["jecur", "merorem", "pascat"]], "jecur": [1, "urat"], "urat": [1, "?"], "montis": [1, "ascenderit"], "ascenderit": [1, "moyses"], "moyses": [1, "cacumen"], "cacumen": [1, "et"], "archam": [1, "foederis"], "foederis": [1, "obumbravit"], "obumbravit": [1, "numen"], "malo": [1, "saginatas"], "saginatas": [1, "carnes"], "triste": [1, "legumen"], "legumen": [1, "."], "odiens": [1, "studium"], "repellam": [1, "paupertatem"], "paupertatem": [1, "fugiens"], "fugiens": [[1, 1], ["vitamque", "amplexatur"]], "vitamque": [1, "misellam"], "misellam": [1, ";"], "ferret": [1, "vigilias"], "vigilias": [1, "frigidamque"], "frigidamque": [1, "cellam"], "cellam": [1, "?"], "tutius": [1, "est"], "jacuisse": [1, "thoro"], "thoro": [1, ","], "tenuisse": [1, "puellam"], "puellam": [1, "."], "gloriantur": [1, "et"], "pede": [1, "socratis"], "socratis": [1, "semper"], "cornicantur": [1, "et"], "dicunt": [[1, 1], [",", "auctores"]], "philosophantur": [1, ","], "divitias": [1, "forsan"], "amatis": [1, ","], "aeternam": [1, "postmodum"], "postmodum": [1, "vitam"], "vitam": [[1, 1], ["capiatis", "dubiis"]], "capiatis": [1, "."], "perditae": [1, "!"], "numquid": [1, "ignoratis"], "ignoratis": [1, ","], "multum": [1, "nocuit"], "fuit": [[1, 1], ["hujus", "aurea"]], "hujus": [[1, 1, 1], ["sortis", "rei", "quia"]], "sortis": [2, ","], "socrates": [1, "legitur"], "legitur": [[1, 1], ["sic", "fore"]], "fuisse": [1, "fortis"], "fortis": [2, "."], "extitit": [1, "magister"], "magister": [1, "cohortis"], "cohortis": [1, "marmoreisque"], "marmoreisque": [1, "satur"], "satur": [1, "iacuit"], "iacuit": [1, "lucanus"], "lucanus": [1, "in"], "hortis": [1, "."], "confert": [1, "pauperi"], "pauperi": [1, "nobilis"], "tityrus": [1, "patula"], "patula": [1, "recubans"], "recubans": [[1, 1], ["sub", ","]], "fago": [1, "?"], "approbo": [1, "rem"], "ago": [1, ";"], "mortis": [[1, 1, 1], ["imago", ",", "rapit"]], "imago": [1, "."], "comitem": [1, "paupertas"], "merorem": [1, ","], "perdit": [1, "fructum"], "fructum": [1, "veneris"], "veneris": [[1, 1], ["et", "laborat"]], "amoris": [1, "florem"], "florem": [1, ","], "juxta": [1, "nobilem"], "nobilem": [1, "versificatorem"], "versificatorem": [1, "non"], "suum": [1, "paupertas"], "pascat": [1, "amorem"], "amorem": [1, "."], "adde": [1, ","], "superbia": [[1, 1], ["sequitur", "mores"]], "inflati": [1, "scientia"], "respuunt": [1, "minores"], "minores": [1, ";"], "impletum": [1, "est"], "egregios": [1, "adiuncta"], "adiuncta": [1, "superbia"], "audi": [2, ","], "socrate": [1, "disputas"], "disputas": [1, "et"], "scribis": [1, ","], "miser": [1, ","], "vaca": [1, "potius"], "potibus": [1, "et"], "cibis": [[1, 1], [";", "crapulatus"]], "noles": [1, "vel"], "nequibis": [1, ","], "utrumque": [1, "tene"], "tene": [1, ","], "medio": [1, "tutissimus"], "tutissimus": [1, "ibis"], "statim": [1, "ut"], "inceperit": [1, "quid"], "philosophari": [1, ","], "inflatur": [1, "occursibus"], "occursibus": [1, "amat"], "amat": [1, "salutari"], "salutari": [1, ","], "laetatur": [1, "ab"], "dari": [[1, 1], ["et", ";"]], "cathedras": [1, "primas"], "primas": [1, ","], "doctor": [1, "ubique"], "ubique": [[1, 1], ["vocari", "saeviat"]], "vocari": [1, "."], "sublimia": [2, ","], "prebet": [1, "acerbum"], "acerbum": [1, ","], "mox": [1, "dilatat"], "dilatat": [[1, 1], ["fimbrias", "chorum"]], "fimbrias": [1, ","], "manifestat": [1, "limbum"], "limbum": [1, "subjectis"], "subjectis": [[1, 1], [",", "tribuat"]], "audiat": [[1, 1], ["sapientis", "qui"]], "sapientis": [1, "verbum"], "desine": [1, "grande"], "frangit": [1, "deus"], "superbum": [1, "."], "velut": [1, "alter"], "alter": [[1, 1], ["igitur", "magis"]], "censorinus": [1, "cato"], "eructat": [1, "parabolas"], "parabolas": [1, "sermone"], "sermone": [1, "cribrato"], "cribrato": [1, ","], "corde": [[1, 1], ["sententias", "mercatum"]], "sententias": [1, "nimium"], "nimium": [1, "elato"], "elato": [1, "eliquat"], "eliquat": [1, "ac"], "tenero": [1, "subplantat"], "subplantat": [1, "verba"], "palato": [1, "."], "stultus": [[1, 1, 1, 1], ["et", ",", "es", "quid"]], "cultu": [1, "destitutus"], "destitutus": [1, ","], "quibusdam": [1, "panniculis"], "panniculis": [1, "verborum"], "verborum": [[1, 1], ["indutus", "mersus"]], "indutus": [1, "videri"], "videri": [1, "prae"], "caeteris": [1, "conatur"], "conatur": [1, "astutus"], "astutus": [1, ","], "rancidulum": [1, "quiddam"], "quiddam": [1, "balba"], "balba": [1, "de"], "nare": [1, "loqutus"], "loqutus": [1, "."], "exultans": [1, "scematibus"], "scematibus": [1, "diversis"], "diversis": [1, "ornari"], "ornari": [1, "se"], "credit": [1, "prae"], "mira": [1, "cornicari"], "cornicari": [1, ","], "auctorem": [1, "noverit"], "fari": [[1, 1], ["metiri", "pauper"]], "metiri": [1, "se"], "propriisque": [1, "iuvari"], "iuvari": [1, "."], "hujsmodi": [1, ","], "diu": [[1, 1], ["fraudet", "teror"]], "fraudet": [1, ","], "desistat": [1, ","], "talibus": [1, "implicari"], "implicari": [1, "gaudet"], "gaudet": [1, ","], "negligat": [1, ","], "aliena": [1, "laudet"], "laudet": [1, ";"], "feliciter": [1, "audet"], "audet": [1, "."], "poenas": [1, "et"], "supplicia": [1, "supremae"], "supremae": [1, "diei"], "diei": [1, "ad"], "reducite": [1, ","], "sancti": [1, "fratres"], "fratres": [1, "mei"], "mei": [[1, 1, 1], [";", "!", ","]], "criminis": [1, "simus"], "simus": [1, "omnes"], "magna": [1, "tamen"], "bonitate": [1, "dei"], "eliconis": [1, "rivulo"], "rivulo": [1, "modice"], "modice": [1, "respersus"], "respersus": [1, "vereor"], "vereor": [1, "ne"], "pondere": [1, "sim"], "sim": [[1, 1], ["verborum", "rea"]], "mersus": [1, ";"], "scriptitat": [1, "mundus"], "universus": [1, ","], "incipe": [1, "menalios"], "menalios": [1, "mecum"], "mecum": [[1, 1], [",", "?"]], "mea": [[1, 1, 1, 1], ["tibia", "gens", ".", "propugnacula"]], "tibia": [1, ","], "accusator": [1, "criminum"], "criminum": [[1, 1], ["judexque", "ardorem"]], "judexque": [1, "sedebo"], "sedebo": [1, "omnium"], "video": [1, "fieri"], "phebo": [[1, 1], [";", "mobilius"]], "vitiosus": [1, "siquidem"], "siquidem": [1, "vitia"], "delebo": [1, ","], "munus": [[1, 1], ["et", "recipit"]], "scribens": [1, "ipse"], "docebo": [1, "."], "dicta": [1, "fuit"], "aurea": [1, "vita"], "proavorum": [1, ","], "simonia": [[1, 1], ["vendicabat", "pullulat"]], "vendicabat": [1, "chorum"], "chorum": [[1, 1], ["nec", ";"]], "regnabant": [1, "scismata"], "scismata": [1, ","], "modernorum": [1, "effodiuntur"], "effodiuntur": [1, "opes"], "irritamenta": [1, "malorum"], "malorum": [1, "."], "papas": [1, "geminos"], "geminos": [1, "instruxere"], "instruxere": [1, "reges"], "adhereas": [1, ","], "nescis": [1, ","], "neges": [1, ";"], "utrobique": [1, "pullulat"], "pullulat": [[1, 1], ["vitiorum", "et"]], "seges": [1, ","], "amissae": [1, "pereunt"], "pereunt": [1, "nullo"], "nullo": [1, "discrimine"], "discrimine": [1, "leges"], "leges": [1, "."], "fortassis": [1, "ecclesia"], "ecclesia": [1, "non"], "jure": [[1, 1], ["repulit", "cathedra"]], "repulit": [1, ","], "cathedra": [1, "dignitatis"], "dignitatis": [1, "extulit"], "extulit": [1, ","], "saepe": [[1, 1], [",", "etenim"]], "male": [[2, 1, 1], ["sibi", "tutum", "dominicum"]], "consulit": [[1, 1], [",", "saluti"]], "crimina": [1, "sepe"], "sepe": [1, "tulit"], "tulit": [1, "."], "christo": [[1, 1], ["neuter", "regentes"]], "neuter": [[1, 1], ["est", "michi"]], "forsitan": [[1, 1], ["electus", "ex"]], "electus": [1, ","], "sufficit": [1, ","], "uterque": [1, "suspectus"], "suspectus": [1, ";"], "nescio": [1, ","], "horum": [1, "sit"], "obliquus": [1, "vel"], "rectus": [1, ","], "diversa": [[1, 1], ["trahunt", "tamen"]], "trahunt": [1, "unum"], "duo": [1, "nomina"], "nomina": [[1, 1], ["pectus", "vana"]], "pectus": [1, "."], "christus": [1, "vineam"], "amodo": [1, "non"], "fodit": [1, ","], "illam": [[1, 1], ["vorat", "scisma"]], "vorat": [1, "ambitus"], "scisma": [[1, 1], ["rodit", ";"]], "sponsa": [[1, 1], ["christi", "dicit"]], "coniugis": [1, "jussa"], "jussa": [1, "non"], "custodit": [1, ","], "etenim": [[1, 1], ["mulier", ","]], "mulier": [1, ","], "coniunx": [[1, 1], ["diligit", "optime"]], "diligit": [1, ","], "odit": [1, "."], "dicit": [[1, 1], ["aput", "dominus"]], "aput": [1, "se"], "teror": [1, "!"], "rapit": [[1, 1], ["impetus", "hora"]], "impetus": [1, "scismatis"], "scismatis": [1, ","], "feror": [1, "?"], "sponsum": [[1, 1], [",", "ad"]], "meus": [1, "hic"], "relevetur": [1, "maeror"], "maeror": [1, ","], "promissum": [1, "tempus"], "tempus": [[1, 1], ["abesse", ","]], "abesse": [1, "quaeror"], "quaeror": [1, "."], "rheus": [1, "opprimit"], "opprimit": [1, ","], "francorum": [1, "chori"], "chori": [1, ","], "dubito": [1, ","], "debeam": [1, "cedere"], "cedere": [1, "favori"], "favori": [1, ";"], "veniat": [[1, 1], ["mors", "terminus"]], "mors": [[1, 1, 1], [",", "inexorabilis", "incerto"]], "terminus": [1, "maerori"], "maerori": [1, "impia"], "impia": [1, "quid"], "dubitas": [1, "dejanira"], "dejanira": [1, "mori"], "mori": [1, "?"], "caesare": [1, "papa"], "statuendus": [1, ","], "secundum": [1, "canones"], "canones": [1, "erat"], "eligendus": [1, ","], "eligitur": [1, "hic"], "reverendus": [1, "."], "colendus": [1, "."], "illi": [1, ","], "hereses": [1, "scismataque"], "scismataque": [1, "vici"], "vici": [1, "quondam"], "facti": [1, "sunt"], "nuper": [1, "inimici"], "inimici": [1, ";"], "cecidi": [1, ","], "stabilis": [1, "non"], "debebam": [1, "dici"], "felicem": [1, "totiens"], "totiens": [1, "iactastis"], "iactastis": [1, ","], "amici": [1, "?"], "gens": [1, "antiquitus"], "nazarea": [1, ","], "sancta": [1, ","], "potuit": [1, ","], "pharisea": [1, ";"], "unam": [1, "duas"], "duas": [1, "faciunt"], "faciunt": [[1, 1], [",", "reos"]], "rea": [1, ","], "praelati": [1, "partiti"], "partiti": [1, "sunt"], "vestimenta": [1, "mea"], "casura": [1, "videor"], "videor": [1, ","], "tota": [1, "nuto"], "nuto": [1, ","], "propugnacula": [1, "muri"], "muri": [1, "carent"], "carent": [1, "scuto"], "scuto": [1, ";"], "aurum": [[1, 1], ["meum", "templi"]], "meum": [1, "scoria"], "scoria": [1, ","], "vilius": [1, "est"], "luto": [1, ","], "princeps": [[1, 1], ["provinciae", "isaac"]], "provinciae": [1, "facta"], "facta": [1, "sub"], "tributo": [1, "."], "turbine": [[1, 1], ["sermonum", "de"]], "sermonum": [1, "caput"], "corruit": [1, ","], "patronum": [1, ";"], "ubinam": [1, "est"], "scipionum": [1, "?"], "marcellusque": [1, "loquax"], "loquax": [1, "et"], "vana": [1, "catonum"], "catonum": [1, "?"], "veni": [[2, 1], [",", "."]], "optime": [1, ","], "turba": [1, "rheni"], "rheni": [1, ","], "glalicis": [1, "lacerant"], "lacerant": [1, "rutheni"], "rutheni": [1, ";"], "tardaveris": [1, ","], "lugentes": [1, "leni"], "leni": [1, ","], "rescribas": [1, ","], "attamen": [[1, 1], ["ipse", "sublimiter"]], "desertam": [1, "creditis"], "creditis": [1, "forsitan"], "hoste": [1, "jam"], "aspiciens": [1, "a"], "venientem": [1, "noto"], "'.": [1, "sic"], "ait": [1, "et"], "longo": [1, "consumit"], "consumit": [1, "gaudia"], "curas": [1, "hominum"], "curis": [1, "depravata"], "depravata": [1, "jam"], "improbata": [1, ";"], "viatores": [1, "devii"], "devii": [1, ","], "curata": [1, ","], "nitimur": [[1, 1], ["in", "per"]], "cupimus": [1, "semperque"], "semperque": [1, "negata"], "negata": [1, "."], "nescimus": [1, "vestigia"], "regni": [1, "nos"], "aeternitas": [1, "non"], "trahit": [[1, 1], ["superni", "optima"]], "superni": [1, ","], "ardentis": [1, "set"], "viam": [[1, 1], ["inferni", ";"]], "inferni": [1, ","], "facilis": [2, "descensus"], "descensus": [2, "averni"], "peccant": [1, "sic"], "fert": [[1, 1], ["malus", "cum"]], "malus": [1, "judicium"], "talis": [1, "turpiter"], "sperni": [1, ","], "instabile": [1, "est"], "laborat": [1, ","], "fraudis": [1, ","], "nodos": [1, "non"], "ignorat": [1, ","], "gloriae": [1, "vanitas"], "colorat": [1, ","], "acta": [1, "probat"], "probat": [1, "."], "vide": [[1, 1], ["maestos", "durum"]], "maestos": [1, "exitus"], "magnis": [1, "in"], "personis": [1, ","], "publicae": [1, "jus"], "conditionis": [1, "."], "circeae": [1, "fugias"], "fugias": [1, "virus"], "virus": [1, "potionis"], "potionis": [1, "!"], "placidis": [1, "abstinuisse"], "abstinuisse": [1, "bonis"], "bonis": [[1, 1], [".", ","]], "omnis": [[1, 1], ["inest", "pellitur"]], "inest": [1, "vanitas"], "speciebus": [1, ","], "mobilius": [1, ","], "lustrat": [1, "phebus"], "phebus": [1, ","], "alternantur": [1, "singula"], "singulis": [1, "diebus"], "diebus": [1, ","], "ludit": [1, "in"], "humanis": [1, "divina"], "divina": [1, "potentia"], "potentia": [1, "rebus"], "inexorabilis": [1, "secum"], "secum": [1, "trahit"], "optima": [[1, 1], [",", "vindictae"]], "parcit": [1, "pessimis"], "parvis": [1, "maxima"], "maxima": [1, ","], "infimis": [1, "sublimia"], "summis": [1, "equat"], "equat": [1, "infima"], "infima": [1, ","], "huc": [1, "omnes"], "domus": [[1, 1, 1], ["est", "domini", "dei"]], "saeviat": [1, "error"], "error": [1, "inconsultus"], "inconsultus": [1, ","], "passim": [1, "praeveniat"], "praeveniat": [1, "sapientem"], "sapientem": [1, "stultus"], "rotundent": [1, "quadrata"], "quadrata": [1, "insani"], "insani": [1, "tumultus"], "consilio": [1, "si"], "velimus": [1, "uti"], "dubiis": [1, "emendemus"], "emendemus": [1, "uti"], "hominis": [1, "consulit"], "saluti": [1, ","], "invia": [1, "virtuti"], "inhabitet": [1, "me"], "constanter": [1, ","], "precor": [1, ","], "pono": [1, "vitium"], "sequor": [1, ","], "quocumque": [[1, 1], ["diverterim", "recipe"]], "diverterim": [1, ","], "sequetur": [1, "decor"], "decor": [1, ","], "forti": [1, "patria"], "patria": [1, "est"], "piscibus": [1, "aequor"], "aequor": [1, "."], "teneri": [1, ";"], "ciconias": [1, "credimus"], "credimus": [1, "maereri"], "maereri": [1, ","], "perdimus": [1, "acquisitum"], "acquisitum": [1, "heri"], "heri": [1, "?"], "minor": [1, "est"], "quaerer": [1, "parta"], "parta": [1, "tueri"], "tueri": [1, "."], "dixisse": [1, "proderit"], "proderit": [1, "de"], "an": [1, "mirabor"], "mirabor": [1, "pecora"], "pecora": [[1, 1], ["vitiis", "volentia"]], "sepulta": [1, ","], "volentia": [1, "semper"], "stulta": [1, "?"], "opponet": [1, "aliquis"], "mordes": [1, ","], "eger": [1, "medicus"], "medicus": [1, ","], "nostras": [1, "audiat"], "defendit": [1, "partes"], "prosunt": [[1, 1], ["domino", "omnibus"]], "domino": [1, ","], "quicumque": [1, "niteris"], "niteris": [1, ","], "stes": [1, "in"], "gemmae": [1, "non"], "immemor": [1, "quamvis"], "quamvis": [1, "obvolutae"], "obvolutae": [1, ";"], "recipe": [1, "verbum"], "salute": [1, ","], "sugit": [1, "apis"], "apis": [1, "etiam"], "etiam": [[1, 1], ["de", "spondent"]], "flore": [[1, 1], ["cicutae", ","]], "cicutae": [1, "."], "es": [2, ","], "exemplum": [1, "fies"], "fies": [1, ","], "fuge": [1, ","], "melior": [1, "aliis"], "corrigi": [1, "non"], "differas": [1, ","], "quies": [1, ","], "vindictae": [1, "proxima"], "proxima": [1, "quaeque"], "quaeque": [1, "dies"], "dies": [1, "."], "inducias": [1, "corrigendi"], "corrigendi": [1, "quaerit"], "sequatur": [1, ","], "videat": [1, ","], "pollutus": [1, "perit"], "perit": [1, ";"], "incerto": [1, "gladio"], "gladio": [1, ","], "etsi": [1, "certa"], "certa": [1, ","], "ferit": [1, "qui"], "cras": [1, "minus"], "aptus": [1, "erit"], "fallax": [1, "est"], "mobilis": [1, "lex"], "lex": [1, "humanae"], "humanae": [1, "sortis"], "necdum": [1, "natis"], "natis": [1, "etiam"], "spondent": [1, "horam"], "ulcio": [1, "semper"], "portis": [1, ","], "instituit": [1, "judex"], "judex": [1, "justus"], "justus": [1, ","], "sperneret": [1, "mundum"], "tutum": [1, ","], "congeriem": [1, "reputans"], "reputans": [1, "in"], "lutum": [1, ","], "conservans": [1, "viriliter"], "viriliter": [1, "corpus"], "corpus": [[1, 1], ["incorruptum", "occidunt"]], "incorruptum": [1, ","], "plane": [1, "diligeret"], "diligeret": [1, "dominus"], "placet": [[1, 1], ["omnibus", "amplius"]], "consuetudo": [1, ","], "amplius": [1, "bursae"], "bursae": [[1, 1], ["plenitudo", "solummodo"]], "plenitudo": [1, ";"], "universos": [1, "allicit"], "cutis": [1, "pulchritudo"], "pulchritudo": [1, ","], "aliquem": [1, "decet"], "sanctitudo": [1, "."], "regentes": [1, ","], "velint": [1, "exsistere"], "exsistere": [1, "benefacientes"], "benefacientes": [1, ","], "exemplorum": [1, "lumine"], "lumine": [1, "tantum"], "relucentes": [1, ","], "laetentur": [1, "pariter"], "exultent": [1, "gentes"], "gentes": [1, "?"], "palacii": [1, "subditis"], "subditis": [1, "conferre"], "conferre": [1, "et"], "modo": [1, "conterant"], "conterant": [1, "totum"], "totum": [1, "mundum"], "guerrae": [1, ","], "afferre": [1, ","], "pace": [1, "maneant"], "maneant": [1, "omnes"], "fines": [1, "terrae"], "terrae": [1, "."], "bellorum": [1, "turbine"], "diffidunt": [1, ","], "norunt": [1, "metuere"], "metuere": [1, ","], "occidunt": [1, ","], "pecuniae": [1, "thesauris"], "thesauris": [1, "confidunt"], "confidunt": [1, ","], "assidos": [1, "et"], "validos": [1, "debiles"], "debiles": [1, "elidunt"], "elidunt": [1, "."], "foris": [1, "suscipiunt"], "suscipiunt": [1, "cultum"], "cultum": [1, "pastoralem"], "pastoralem": [1, ","], "degustati": [1, "sunt"], "cenam": [1, "spiritalem"], "spiritalem": [1, ","], "habentes": [1, "apud"], "vestem": [1, "nupcialem"], "nupcialem": [1, ","], "agentes": [1, "operibus"], "operibus": [1, "curam"], "curam": [1, "mercennalem"], "mercennalem": [1, "."], "timidos": [1, "efficit"], "efficit": [1, "potestas"], "potestas": [1, "et"], "afficit": [1, "pauperum"], "pauperum": [1, "aegestas"], "aegestas": [1, ","], "districti": [1, "judicis"], "opprimet": [1, "majestas"], "majestas": [1, ","], "circuitu": [1, "valida"], "valida": [1, "tempestas"], "tempestas": [1, "."], "avariciae": [1, "coeunt"], "coeunt": [1, "caecatum"], "caecatum": [1, ","], "psalmos": [1, "ruminant"], "ruminant": [1, ","], "mercatum": [1, ";"], "nonne": [[1, 1], [",", "ex"]], "cogitant": [1, "domini"], "mandatum": [1, ","], "eorum": [1, "oracio"], "oracio": [1, "fiet"], "fiet": [1, "in"], "peccatum": [1, "?"], "habundes": [1, "in"], "capite": [1, "cano"], "cano": [1, "senectutis"], "senectutis": [1, "retinent"], "retinent": [1, "in"], "moenibus": [1, "flores"], "flores": [1, "juventutis"], "juventutis": [1, ";"], "conscii": [1, "de"], "insectantur": [1, "alios"], "gladios": [1, "acutis"], "acutis": [1, "."], "iis": [1, "esse"], "novimus": [1, "plures"], "sodomaeos": [1, "deas"], "deas": [1, "non"], "recipere": [1, "set"], "amare": [1, "deos"], "quotquot": [1, "invenerit"], "invenerit": [1, "hujus"], "coelis": [[1, 1], ["habitat", "!"]], "habitat": [1, "irridebit"], "irridebit": [1, "eos"], "eos": [[1, 1], [".", "non"]], "pascunt": [1, ","], "ipsimet": [1, "pocius"], "pocius": [1, "pascantur"], "pascantur": [1, ","], "humilium": [1, "praeces"], "praeces": [1, "inclinantur"], "inclinantur": [1, ","], "sublimiter": [1, "eis"], "eis": [1, "dominantur"], "dominantur": [1, ";"], "confundantur": [1, "pariter"], "revereantur": [1, "."], "implementum": [1, "nec"], "familiis": [1, "dividunt"], "dividunt": [1, "frumentum"], "frumentum": [1, ","], "dominicum": [1, "duplicant"], "duplicant": [1, "talentum"], "talentum": [1, "."], "veterescunt": [1, "miseri"], "miseri": [[1, 1], ["sicut", "fata"]], "vestimentum": [1, "!"], "mirreo": [1, "praesuli"], "praesuli": [1, "similis"], "similis": [1, "nunc"], "mna": [1, "hujus"], "mnas": [1, "decem"], "decem": [1, "acquisivit"], "acquisivit": [1, ","], "ea": [1, "dominus"], "praemia": [1, "ascivit"], "ascivit": [1, ","], "oculus": [1, "nec"], "aures": [1, "audivit"], "audivit": [1, "."], "paucos": [1, "sibi"], "paulinus": [1, "et"], "condam": [1, "habuit"], "habuit": [1, "patrem"], "patrem": [1, "mons"], "mons": [1, "cassinus"], "cassinus": [1, ","], "qualis": [1, "exstitit"], "exstitit": [1, "pastor"], "pastor": [[1, 1], ["tudertinus", "ovium"]], "tudertinus": [1, ","], "consimiles": [1, "ecclesiae"], "ecclesiae": [1, "sinus"], "sinus": [1, "."], "sanctulum": [1, "praesbyterum"], "praesbyterum": [1, "nolumus"], "nolumus": [1, "tacere"], "tacere": [1, "qui"], "proximo": [1, "voluit"], "carere": [1, ";"], "legere": [1, "\""], "exibis": [1, ","], "avidi": [1, "tumore"], "tumore": [1, "bursarum"], "bursarum": [1, ","], "multiplicat": [1, "fons"], "diviciarum": [1, ","], "desiderat": [[1, 1], ["congestus", "ad"]], "congestus": [1, "earum"], "earum": [1, "ut"], "cervus": [1, "desiderat"], "fontes": [1, "aquarum"], "aquarum": [1, "."], "adiunt": [1, "ab"], "pharisaei": [[1, 1], ["quod", ","]], "taceo": [1, "tantae"], "tantae": [1, "reos"], "cantabo": [1, "suppliciter"], "suppliciter": [1, "in"], "conspectu": [1, "dei"], "domine": [1, "miserere"], "miserere": [1, "mei"], "ausculta": [1, ","], "habens": [1, "tam"], "thesauros": [1, "congreges"], "congreges": [1, ","], "estimo": [1, "non"], "aequum": [1, ","], "loquar": [1, "tecum"], "tecum": [1, "\""], "denario": [1, "convenisti"], "convenisti": [1, "mecum"], "ovium": [1, ","], "vivere": [1, "si"], "velis": [1, ","], "pugnato": [1, "pro"], "manibus": [1, "et"], "telis": [1, "sis"], "domo": [1, "domini"], "prudens": [1, "et"], "laudare": [1, "valeas"], "valeas": [1, "dominum"], "dominum": [1, "de"], "dilabatur": [1, "inpii"], "inpii": [1, "regnum"], "regnum": [1, "pharaonis"], "pharaonis": [1, ","], "aebrea": [1, "premitur"], "premitur": [1, ","], "spoliata": [1, "bonis"], "saul": [1, "non"], "compescitur": [1, "musicorum"], "musicorum": [1, "tonis"], "tonis": [1, "."], "infulatum": [1, "aaron"], "aaron": [1, "delectatur"], "delectatur": [1, "donis"], "donis": [1, "."], "templum": [[1, 1], ["dei", "sustinentes"]], "violat": [1, "ordo"], "ordo": [1, "praelatorum"], "praelatorum": [[1, 1], [",", "mentes"]], "fuscinis": [1, "carnes"], "cacaborum": [1, ";"], "semen": [1, "chanaan"], "chanaan": [1, ","], "duces": [1, "reproborum"], "reproborum": [1, ","], "spiritus": [[1, 1, 1], ["fiunt", "karisma", "sacrosanctum"]], "vile": [1, "forum"], "forum": [[1, 1, 1], [".", ";", "nullus"]], "patrum": [1, "princeps"], "isaac": [1, "olim"], "excaecatus": [1, "jacob"], "recipit": [1, ";"], "eo": [1, "saciatus"], "saciatus": [1, "benedixit"], "benedixit": [1, "israel"], "primo": [1, "natus"], "natus": [1, "longum"], "longum": [1, "flevit"], "flevit": [1, "esau"], "esau": [1, "quasi"], "reprobatus": [1, "."], "excaecati": [1, "praesules"], "rectam": [1, "linquunt"], "linquunt": [1, "viam"], "amplexatur": [1, "liam"], "liam": [1, ";"], "laesus": [1, "claudicat"], "claudicat": [1, "vulneratus"], "vulneratus": [1, "sciam"], "sciam": [1, ","], "futuri": [1, "legitur"], "fore": [1, "prophetiam"], "prophetiam": [1, "."], "terminabit": [1, "dominus"], "sophisma": [1, ","], "venit": [[1, 1], ["scandalum", "scisma"]], "scandalum": [1, ","], "sacros": [1, "vendunt"], "ordines": [1, ","], "sacrum": [1, "vendunt"], "crisma": [1, ";"], "karisma": [1, "."], "praebende": [1, "nunc"], "temporis": [1, "ducuntur"], "ducuntur": [1, "ad"], "disperdet": [1, "dominus"], "iter": [1, "inpiorum"], "inpiorum": [1, ","], "conquassabit": [1, "capita"], "capita": [1, "in"], "terra": [1, "multorum"], "multorum": [1, "."], "inaudita": [1, "dicerem"], "dicerem": [1, ","], "liceat": [1, "fari"], "pellitur": [1, "procul"], "altari": [1, "postquam"], "postquam": [1, "sentit"], "sentit": [1, "pontifex"], "posse": [1, "dari"], "paupere": [1, "spondeat"], "spondeat": [1, "scolari"], "scolari": [1, "."], "mendicat": [1, "misere"], "chorus": [1, "poetarum"], "poetarum": [1, "nulli"], "imbui": [1, "fonte"], "litterarum": [1, ";"], "huic": [1, ","], "absque": [[1, 1, 1], ["munere", "flore", "mora"]], "munere": [1, "praesul"], "carum": [1, "."], "columpnae": [1, "titubant"], "titubant": [1, "templum"], "sustinentes": [1, ","], "pervertunt": [1, "munera"], "credo": [1, "quod"], "sorbeat": [1, "tartarus"], "tartarus": [1, "viventes"], "viventes": [1, ","], "tribuunt": [1, "simonem"], "simonem": [1, "sequentes"], "sequentes": [1, "."], "templi": [1, "penitus"], "redditur": [1, "obscurum"], "obscurum": [1, ","], "reaedificant": [1, "babilonis"], "babilonis": [1, "murum"], "spelunca": [1, "furum"], "furum": [1, ","], "quibus": [1, "contra"], "stimulum": [1, "calcitrare"], "calcitrare": [1, "durum"], "evangelizantium": [1, "sordidantur"], "sordidantur": [1, "pedes"], "pedes": [1, ","], "credunt": [1, "sordidum"], "sordidum": [1, "simonis"], "simonis": [1, "haeredes"], "haeredes": [1, ";"], "alienas": [1, "vacuant"], "vacuant": [1, ","], "suas": [1, "implent"], "implent": [1, "aedes"], "aedes": [1, ","], "tribunal": [1, "vertitur"], "vertitur": [1, "pastoralis"], "sedes": [1, "."], "aret": [1, "sicca"], "sicca": [1, "penitus"], "ficus": [1, "absque"], "gedeonis": [1, "area"], "area": [1, "dulci"], "dulci": [1, "caret"], "caret": [1, "rore"], "rore": [1, ";"], "praelatos": [1, "miseri"], "fata": [1, "monent"], "monent": [1, "core"], "core": [1, ","], "consimili": [1, "pereant"], "pereant": [1, "dolore"], "dolore": [1, "."], "secare": [1, "nequeam"], "nequeam": [1, ","], "fungor": [1, "vice"], "cotis": [1, ","], "imitantur": [1, "praesules"], "remotis": [1, ";"], "nullus": [1, "circuit"], "circuit": [1, "orbem"], "orbem": [1, "in"], "melotis": [1, ","], "immo": [[1, 1], ["mundus", "pharisaei"]], "viribus": [1, "almpexatur"], "almpexatur": [1, "totis"], "totis": [1, "."], "verum": [[1, 1], ["fatear", "latuit"]], "fatear": [1, ","], "causa": [1, "mei"], "zelus": [1, "domus"], "regunt": [1, "praesules"], "subjectos": [1, "faciunt"], "ferunt": [1, "opera"], "opera": [1, ","], "multos": [1, "cruciatus"], "secretum": [1, "thalami"], "thalami": [1, "paucis"], "paucis": [1, "comitatus"], "crapulatus": [1, ","], "delet": [1, "vino"], "vino": [[1, 1], ["veteri", "."]], "veteri": [1, "populi"], "populi": [1, "reatus"], "reatus": [1, "."], "patitur": [1, "nomine"], "trino": [1, ";"], "hiemali": [1, "tempore"], "proximus": [1, "camino"], "camino": [1, ","], "vinum": [1, "forte"], "redolet": [1, "ore"], "resupino": [1, "posses"], "posses": [1, "sine"], "poculo": [1, "satiari"], "satiari": [1, "vino"], "ora": [1, "!"], "more": [1, "fluminum"], "fluminum": [1, ","], "fluit": [1, "absque"], "mora": [1, ";"], "pueros": [1, "mortis"], "hora": [1, ","], "retinere": [1, "lora"], "lora": [1, "."], "exoremus": [[1, 1], ["igitur", "iterum"]], "summum": [1, "creatorem"], "vincimus": [1, "pravum"], "pravum": [1, "exactorem"], "exactorem": [1, ","], "det": [1, "nobis"], "sacrosanctum": [1, "rorem"], "rorem": [1, "extinguendo"], "extinguendo": [1, "penitus"], "ardorem": [1, "."], "iterum": [1, "matrem"], "matrem": [1, "pietatis"], "pietatis": [1, ","], "latuit": [1, "numen"], "deitatis": [1, ","], "tribuat": [1, "simul"], "simul": [1, "et"], "praelatis": [1, "vivo"], "vivo": [1, "semper"], "perfrui": [1, "pane"], "pane": [1, "caritatis"], "caritatis": [1, "."]}}, "backward": null}